Workbook

Sheet SITUACION COMERCIAL
A4: Actualización30/08/2024
A5: VENTAS | B5: =COUNTIF($A$12:$A$77,"RESERVADO") | E5: CUADRO MAESTRO DE SITUACIÓN (Actualización precios 11/06/2024)
A6: % s/unid.: | B6: =+$B$5/66 | C6: % S/importe.: | D6: =+#REF!/#REF!
A8: ESTADO | E8: INMUEBLES | N8: SUPERFICIES VIVIENDA (m2) | S8: PRECIOS | V8: FORMA DE PAGO ESTANDAR (IVA inlcuido) | AB8: DATOS CONTACTO COMPRADORES | AM8: INVESTICACION
E9: Nº Orden | F9: VIVIENDA | J9: ANEXOS | N9: Sup. Útil vivienda | O9: Sup. Útil terraza (50%) | P9: Sup.út Vvda. pp.terraz cubierta | Q9: Sup. Construida propia | R9: sup. patio/terraza desubieta | S9: Neto | T9: IVA | U9: TOTAL | V9: Reserva | W9: Compraventa | X9: Durante obra(20 pagos) | Y9: A llaves | Z9: Hipoteca contrato | AA9: Finca Registral
A10: Reservas: | B10: Fecha Reserva | C10: Fecha compravent. | F10: PORTAL | G10: PLANTA | H10: LETRA | I10: Nº Dorm. | J10: Garaje | K10: Trastero | L10: G. Adicional | M10: Tr. Adicional | AB10: TITULAR 1 | AE10: MAIL 1 | AF10: TITULAR 2 | AI10: MAIL 2 | AJ10: Situacion familiar | AK10: Dirección Contrato | AM10: cargas familiares | AN10: EDAD | AO10: Profecsión | AP10: €/mes | AQ10: EDAD | AR10: Profesión | AS10: €/mes | AT10: Hipoteca | AU10: Vende | AV10: Motivo compra | AX10: Procede
A12: BLOQUEADO | E12: 1 | F12: 1 | G12: BAJA | H12: A | I12: 4 | J12: 62 | K12: 56 | L12: . | M12: . | N12: 109.9 | O12: 9.52 | P12: 119.42 | Q12: 139.96 | R12: 25.81 | S12: 310000 | T12: 31000 | U12: 341000 | V12: 0 | W12: 0 | X12: 0 | Y12: 93000 | Z12: 248000 | AA12: 49350 | AM12: si | AN12: 34 | AO12: Ing. Informatico | AQ12: 41 | AR12: Direct. Escuela Infantil | AX12: Pardaleras | BB12: =IF(A12="RESERVADO",S12,"LIBRE")
A13: RESERVADO | B13: 44785 | C13: 45383 | E13: 2 | F13: 1 | G13: BAJA | H13: B | I13: 3 | J13: 57 | K13: 50 | L13: . | M13: . | N13: 90.04 | O13: 3.17 | P13: 93.21 | Q13: 107.77 | R13: 33.92 | S13: 234900 | T13: 23490 | U13: 258390 | V13: 12000 | W13: 20000 | X13: 19678 | Y13: 18792 | Z13: 187920 | AA13: =AA12+2 | AB13: MANUEL PEÑA GRAGERA | AE13: manuel.pgragera@gmail.com | AF13: JUAN FRANCISCO CERRATO MIRA | AI13: jfra_0099@hotmail.com | AJ13: soltero | AK13: C/. Eugenio Garcia Estop 16, 4ºD de Badajoz | AM13: no | AN13: 31 | AO13: Medico | AP13: 3000 | AQ13: 33 | AR13: Maestro | AS13: 2300 | AT13: 0.8 | AU13: No | AV13: 1ª vivienda | AX13: Ronda Norte | BB13: =IF(A13="RESERVADO",S13,"LIBRE") | BC13: ES57 0128 0060 5101 0005 4931
A14: RESERVADO | B14: 027/05/2023 | C14: 45534 | E14: 3 | F14: 1 | G14: BAJA | H14: C | I14: 2 | J14: NO | K14: 49 | L14: . | N14: 73.05 | O14: 3.3 | P14: 76.35 | Q14: 89.43 | R14: 0 | S14: 153000 | T14: 15300 | U14: 168300 | V14: 4950 | W14: 13563 | X14: 6732 | Y14: 20655 | Z14: 122400 | AA14: =AA13+2 | AB14: ISABEL PEREZ CORRALES | AE14: isabelperez57@hotmail.com | AK14: C/. Clavellinas 25, 1ºC de Badajoz | AM14: no | AN14: 63 | AO14: Funcionario | AP14: 1500 | AT14: 0 | AU14: no | AV14: Reposicion | AX14: Ciudad Jardin | BB14: =IF(A14="RESERVADO",S14,"LIBRE") | BC14: ES36 0182 0386 5702 0800 0441
A15: RESERVADO | B15: 45336 | C15: 45392 | E15: 4 | F15: 1 | G15: BAJA | H15: D | I15: 2 | J15: 40 | K15: 60 | L15: . | M15: . | N15: 70.72 | O15: 0 | P15: 70.72 | Q15: 85.24 | R15: 15.23 | S15: 178000 | T15: 17800 | U15: 195800 | V15: 5874 | W15: 19580 | X15: 5874 | Y15: 22072 | Z15: 142400 | AA15: =AA14+2 | AB15: ISIDORA ROMERO MARTIN | AE15: isiromeromartin@hotmail.com | AF15: ….............. | AK15: C/. Ramón y Cajal 15, Monterrubio de la Serena (Badajoz) | AN15: 52 | BB15: =IF(A15="RESERVADO",S15,"LIBRE") | BC15: ES70 2103 7308 9100 1002 6799
A16: RESERVADO | C16: 45842 | E16: 5 | F16: 1 | G16: BAJA | H16: E | I16: 2 | J16: 42 | K16: 18 | L16: . | M16: . | N16: 67.94 | O16: 0 | P16: 67.94 | Q16: 79.14 | R16: 29.89 | S16: 215000 | T16: 21500 | U16: 236500 | V16: 0 | W16: 28380 | X16: 7095 | Y16: 29025 | Z16: 172000 | AA16: =AA15+2 | AB16: JOKIN MIRAGAYA FERNANDEZ | AE16: jokin.miragaya@gmail.com | AF16: MARIA FERNANDEZ ROMERO | AJ16: casados | AK16: C/. GRPO. ALDATZE ETXADIA 21C - GALDAKAO (BIZKAIA) | BB16: =IF(A16="RESERVADO",S16,"LIBRE") | BC16: ES43 3035 0424 85 42410 36701
A17: RESERVADO | B17: 45356 | C17: 45383 | E17: 6 | F17: 1 | G17: 1 | H17: A | I17: 4 | J17: 9 | K17: 13 | L17: - | M17: . | N17: 111.09 | O17: 10.13 | P17: 121.22 | Q17: 142.57 | S17: 303400 | T17: 30340 | U17: 333740 | V17: 10012.2 | W17: 33374 | X17: 16687 | Y17: 30946.8 | Z17: 242720 | AA17: =AA16+2 | AB17: JOSE MARIA PRUDENCIO ALONSO | AF17: ANTONIA HERMOSA LOPEZ | AI17: hermosalopezantonia@gmail.com | AJ17: casados | AK17: C/. Castillo de Alconchel 26, 5, 1ºD | BB17: =IF(A17="RESERVADO",S17,"LIBRE") | BC17: ES54 2085 4508 3103 3145 5319
A18: RESERVADO | C18: 45903 | E18: 7 | F18: 1 | G18: 1 | H18: B | I18: 3 | J18: 12 | K18: 16 | L18: . | M18: . | N18: 93.26 | O18: 5.77 | P18: 99.03 | Q18: 115.43 | S18: 262000 | T18: 26200 | U18: 288200 | V18: 0 | W18: 34584 | X18: 8646 | Y18: 35370 | Z18: 209600 | AA18: =AA17+2 | AB18: ANA BELEN GOMEZ CABELLO | AE18: ana.cab.gom@hotmail.com | AJ18: soltera | AK18: C/ RAFAEL LUCENQUI 8, LOCAL ACADEMIA EDUCO 06004 | BB18: =IF(A18="RESERVADO",S18,"LIBRE") | BC18: ES71 1465 0100 9520 5664 0765
A19: RESERVADO | B19: 44720 | C19: 45415 | E19: 8 | F19: 1 | G19: 1 | H19: C | I19: 2 | J19: 54 | K19: 48 | L19: . | M19: . | N19: 71.38 | O19: 4.35 | P19: 75.73 | Q19: 87.48 | S19: 173818 | T19: 17381.8 | U19: 191199.8 | V19: 9724 | W19: 19119.99 | X19: 9396 | Y19: 13905.41 | Z19: 139054.4 | AA19: =AA18+2 | AB19: AMALIA CABANILLAS | AE19: amaliaahabilitados@gmail.com | AF19: PABLO JOSE DIAZ MARCOS | AI19: pablojosediaz@yahoo.es | AJ19: soltero | AK19: C/. Castillo de Zafra 3, 3ªB | AM19: no | AN19: 49 | AO19: Abogada | AP19: 1800 | AQ19: 47 | AR19: Empresario | AS19: 3000 | AT19: 0.8 | AU19: no | AV19: Reposición | AW19: Mejora | AX19: U. Guadiana | BB19: =IF(A19="RESERVADO",S19,"LIBRE") | BC19: ES17 1465 0100 94 1753450826
A20: RESERVADO | C20: 46008 | E20: 9 | F20: 1 | G20: 1 | H20: D | I20: 2 | J20: 10 | K20: 14 | L20: . | M20: . | N20: 64.33 | O20: 2.04 | P20: 66.37 | Q20: 77.92 | S20: 209000 | T20: 20900 | U20: 229900 | V20: 0 | W20: 34485 | X20: 0 | Y20: 28215 | Z20: 167200 | AA20: =AA19+2 | AB20: JACINTA GALLEGO SANCHEZ | AE20: jacintagallego20@gmail.com | AK20: C/. Julio Cinfuegos Linares 12, 3ºA - Badajoz | BB20: =IF(A20="RESERVADO",S20,"LIBRE")
A21: RESERVADO | B21: 45194 | C21: 45401 | E21: 10 | F21: 1 | G21: 1 | H21: E | I21: 2 | J21: 48 | K21: . | L21: . | M21: . | N21: 67.18 | O21: 3 | P21: 70.18 | Q21: 85.32 | S21: 178000 | T21: 17800 | U21: 195800 | V21: 6280 | W21: 19580 | X21: 9790 | Y21: 17750 | Z21: 142400 | AA21: =AA20+2 | AB21: VICTOR JOSE ROJAS MORENO | AE21: v.rojas@cnat.es | AK21: C/. Antonio Concha 78, 5, Navalmoral de la Mata (CC) | AN21: 45 | AO21: Trab. Central Nuclear | BB21: =IF(A21="RESERVADO",S21,"LIBRE") | BC21: ES04 0049 2522 6421 1509 5944
A22: RESERVADO | B22: …............ | C22: 45490 | E22: 11 | F22: 1 | G22: 1 | H22: F | I22: 2 | J22: 14 | K22: 21 | L22: . | M22: . | N22: 67.94 | O22: 3.62 | P22: 71.56 | Q22: 82.42 | S22: 185000 | T22: 18500 | U22: 203500 | V22: 0 | W22: 22385 | X22: 9157.5 | Y22: 23957.5 | Z22: 148000 | AA22: =AA21+2 | AB22: JUAN MANUEL DURAN GUERRERO | AE22: madugue@hotmail.com | AF22: MARIA JOSE JIMENEZ MURIEL | AK22: Travesia Arturo Barea 28, Merida (Badajoz) | BB22: =IF(A22="RESERVADO",S22,"LIBRE") | BC22: ES87 3009 0010 5221 1675 0429
A23: RESERVADO | B23: 44642 | C23: 45371 | E23: 12 | F23: 1 | G23: 2 | H23: A | I23: 4 | J23: 60 | K23: 54 | L23: . | M23: . | N23: 110.85 | O23: 10.78 | P23: 121.63 | Q23: 143.26 | S23: 279900 | T23: 27990 | U23: 307890 | V23: 9236.7 | W23: 30789 | X23: 15394.5 | Y23: 28549.8 | Z23: 223920 | AA23: =AA22+2 | AB23: IGNACIO AMARO BLANCO | AE23: iamaroblanco@gmail.com | AF23: ALBA GONZALEZ HABA MARTINEZ | AI23: alba.ghm@gmail.com | AJ23: casados | AK23: C/. Antonio de Nebrija, 6 A, 2 esc izq, 1ºB de Badajoz | AM23: no | AN23: 35 | AO23: Ing. Agronomo | AP23: 1800 | AQ23: 32 | AR23: Medico | AS23: 2200 | AT23: 0.8 | AU23: no | BB23: =IF(A23="RESERVADO",S23,"LIBRE") | BC23: ES55 0049 5525 5620 1103 8674
A24: RESERVADO | B24: 44669 | C24: 45383 | E24: 13 | F24: 1 | G24: 2 | H24: B | I24: 3 | J24: 13 | K24: 20 | L24: . | M24: . | N24: 93.39 | O24: 5.77 | P24: 99.16 | Q24: 115.43 | S24: 238600 | T24: 23860 | U24: 262460 | V24: 7873.8 | W24: 26246 | X24: 13123 | Y24: 24337.2 | Z24: 190880 | AA24: =AA23+2 | AB24: SATURNINO GONZALEZ -HABA GIL | AE24: ninoghg@gmail.com | AF24: MARIA ISABEL MARTINEZ FERNANDEZ | AI24: marisa63@educarex.es | AJ24: casados | AK24: C/. Condes de Cartagena 25, Villanueva de la Serena (Badajoz) | AM24: no | AN24: 56 | AO24: Profesor | AP24: 2400 | AQ24: 59 | AR24: Profesora | AS24: 2500 | AT24: 0.3 | AV24: reposición | AW24: para jubilacion | AX24: Otra localidad (hijos compran tambien) | BB24: =IF(A24="RESERVADO",S24,"LIBRE") | BC24: ES13 0049 5346 7123 1695 1598
A25: RESERVADO | B25: 44658 | C25: 45371 | E25: 14 | F25: 1 | G25: 2 | H25: C | I25: 2 | J25: 44 | K25: 43 | L25: . | M25: . | N25: 71.37 | O25: 4.35 | P25: 75.72 | Q25: 89.07 | S25: 178900 | T25: 17890 | U25: 196790 | V25: 9839.5 | W25: 19679 | X25: 9839.5 | Y25: 14312 | Z25: 143120 | AA25: =AA24+2 | AB25: JUAN FRANCISCO OTERO MARTIN | AE25: jfoteromartin@gmail.com | AF25: ---------------- | AJ25: divorciado | AK25: C/. Damian Tellez la Fuente 18, 4º D de Badajoz | AM25: no | AN25: 69 | AO25: Jubilado | AP25: 2100 | AT25: 0 | AU25: no | AV25: reposición | AW25: menor tamaño | AX25: Valdepasillas | BB25: =IF(A25="RESERVADO",S25,"LIBRE") | BC25: ES62 0049 4640 9022 9507 3949
A26: RESERVADO | C26: 45442 | E26: 15 | F26: 1 | G26: 2 | H26: D | I26: 2 | J26: 15 | K26: 22 | L26: . | M26: . | N26: 67.94 | O26: 3.1 | P26: 71.04 | Q26: 82.42 | S26: 185000 | T26: 18500 | U26: 203500 | V26: 0 | W26: 22385 | X26: 10175 | Y26: 22940 | Z26: 148000 | AA26: =AA25+2 | AB26: MARIA JESUS FERNANDEZ SANCHEZ | AE26: mariaj.fs.88@gmail.com | AJ26: soltera | AK26: C/. Camelia 15, 2ºC - Navalmoral de la Mata (Cáceres) | BB26: =IF(A26="RESERVADO",S26,"LIBRE") | BC26: ES58 0049 2522 6729 9586 4137
A27: RESERVADO | B27: 45336 | C27: 45392 | E27: 16 | F27: 1 | G27: 2 | H27: E | I27: 2 | J27: 58 | K27: 51 | N27: 64.07 | O27: 2.68 | P27: 66.75 | Q27: 85.32 | S27: 181000 | T27: 18100 | U27: 199100 | V27: 5973 | W27: 19910 | X27: 9955 | Y27: 18462 | Z27: 144800 | AA27: =AA26+2 | AB27: MANUEL JOSE SUAREZ MARTIN | AE27: pepe.jerepe83@gmail.com | AK27: C/. Diputación 25, Monterrubio de la Serena (Badajoz) | AN27: 40 | BB27: =IF(A27="RESERVADO",S27,"LIBRE") | BC27: ES65 0078 0059 3240 1000 2962
A28: RESERVADO | C28: 45504 | E28: 17 | F28: 1 | G28: 2 | H28: F | I28: 2 | J28: 43 | K28: 42 | L28: . | M28: . | N28: 67.94 | O28: 3.1 | P28: 71.04 | Q28: 82.42 | S28: 187000 | T28: 18700 | U28: 205700 | V28: 0 | W28: 22627 | X28: 8228 | Y28: 25245 | Z28: 149600 | AA28: =AA27+2 | AB28: MARIA DURAN ENTISNE | AE28: maria.despachoduran@gmail.com | AJ28: soltera | AK28: C/. Conde Barcelona 9, 5º A - Badajoz | BB28: =IF(A28="RESERVADO",S28,"LIBRE") | BC28: ES97 3009 0091 8021 1575 2517
A29: RESERVADO | B29: 44642 | C29: 45383 | E29: 18 | F29: 1 | G29: 3 | H29: A | I29: 4 | J29: 59 | K29: 53 | L29: 50 | M29: . | N29: 110.85 | O29: 11.4 | P29: 122.25 | Q29: 140.49 | S29: 300100 | T29: 30010 | U29: 330110 | V29: 16605.5 | W29: 33011 | X29: 14000 | Y29: 26413.5 | Z29: 240080 | AA29: =AA28+2 | AB29: DIEGO GARCIA RUBIO | AE29: miotracuenta2@gmail.com | AF29: SARA ESPINA HIDALGO | AI29: sespinah@gmai.com | AJ29: casados | AK29: C/. Castillo Puebla de Alcocer, 32, 2ºA de Badajoz | AM29: hijos | AN29: 58 | AO29: Veterinario | AP29: 2300 | AQ29: 56 | AR29: Bibliotecaria | AS29: 2500 | AT29: 0.8 | AU29: consideraran | AV29: Reposición | AX29: U. Guadiana | BB29: =IF(A29="RESERVADO",S29,"LIBRE") | BC29: ES33 0049 0373 6025 9167 2500
A30: RESERVADO | B30: 44650 | C30: 45386 | E30: 19 | F30: 1 | G30: 3 | H30: B | I30: 3 | J30: 16 | K30: 23 | L30: . | M30: . | N30: 93.39 | O30: 5.77 | P30: 99.16 | Q30: 115.43 | S30: 239700 | T30: 23970 | U30: 263670 | V30: 14184 | W30: 25367 | X30: 13183 | Y30: 19176 | Z30: 191760 | AA30: =AA29+2 | AB30: FELIPA PEREZ CORRALES | AE30: felipaperezcorrales@gmail.com | AK30: C/. Madame Curie 209, 1ºB de Cáceres | AM30: no | AN30: 63 | AO30: Funcionario | AP30: 1500 | AT30: 0 | AU30: no | AV30: Reposicion | AX30: Otra localidad (Cáceres) | BB30: =IF(A30="RESERVADO",S30,"LIBRE") | BC30: ES60 3009 0110 9628 2475 4325
A31: RESERVADO | B31: 44648 | C31: 45383 | E31: 20 | F31: 1 | G31: 3 | H31: C | I31: 2 | J31: 38 | K31: 25 | L31: . | M31: . | N31: 71.37 | O31: 2.54 | P31: 73.91 | Q31: 87.14 | R31: 3.62 | S31: 181600 | T31: 18160 | U31: 199760 | V31: 9988 | W31: 19976 | X31: 9988 | Y31: 14528 | Z31: 145280 | AA31: =AA30+2 | AB31: PAULINO CONEJO NAVARRETE | AE31: paulino.conejo@hotmail.com | AF31: ---------------- | AJ31: casado | AK31: Plaza de la Constitución 2, 1ºAB de Badajoz | AN31: 72 | AO31: jubilado | AT31: 0 | AU31: no | AV31: Inversión | AX31: Pardaleras | BB31: =IF(A31="RESERVADO",S31,"LIBRE") | BC31: ES30 2080 3578 80030 4008 5577
A32: RESERVADO | B32: 44874 | C32: 45383 | E32: 21 | F32: 1 | G32: 3 | H32: D | I32: 2 | J32: 45 | K32: 44 | L32: . | M32: . | N32: 67.94 | O32: 3.1 | P32: 71.04 | Q32: 82.42 | S32: 184000 | T32: 18400 | U32: 202400 | V32: 10120 | W32: 20240 | X32: 10120 | Y32: 14720 | Z32: 147200 | AA32: =AA31+2 | AB32: PAULINO CONEJO NAVARRETE | AE32: paulino.conejo@hotmail.com | AF32: ---------------- | AJ32: casado | AK32: Plaza de la Constitución 2, 1ºAB de Badajoz | AN32: 72 | AO32: jubilado | AT32: 0 | AU32: no | AV32: Inversión | AX32: Pardaleras | BB32: =IF(A32="RESERVADO",S32,"LIBRE") | BC32: ES30 2080 3578 80030 4008 5577
A33: RESERVADO | B33: 45330 | C33: 45397 | E33: 22 | F33: 1 | G33: 3 | H33: E | I33: 2 | J33: 11 | K33: 15 | L33: . | M33: . | N33: 64.07 | O33: 2.68 | P33: 66.75 | Q33: 85.32 | S33: 184000 | T33: 18400 | U33: 202400 | V33: 6072 | W33: 20240 | X33: 10120 | Y33: 18768 | Z33: 147200 | AA33: =AA32+2 | AB33: TRINIDAD VILLALOBOS SAAVEDRA | AE33: trivillasa@gmail.com | AF33: ….............. | AK33: Av. Miguel Angel Celdran Matu, 14 -4ºIz, Badajoz | BB33: =IF(A33="RESERVADO",S33,"LIBRE") | BC33: ES06 0182 2874 0502 0158 0919
A34: RESERVADO | B34: 44874 | C34: 45397 | E34: 23 | F34: 1 | G34: 3 | H34: F | I34: 2 | J34: 51 | K34: 46 | L34: . | M34: . | N34: 67.94 | O34: 3.1 | P34: 71.04 | Q34: 82.42 | S34: 184000 | T34: 18400 | U34: 202400 | V34: 10120 | W34: 20240 | X34: 10120 | Y34: 14720 | Z34: 147200 | AA34: =AA33+2 | AB34: MARIA JOSEFA MANCHADO MORAGA | AE34: majosevva@gmail.com | AF34: MIGUEL ANGEL GARCIA OLIVARES | AJ34: casado | AK34: C/. Eduardo Pino 21 de Villanueva de la Serena (Badajoz) | AM34: hios | AN34: 49 | AO34: Profesora | AP34: 2300 | AQ34: 51 | AR34: Autonomo | AS34: 1800 | AT34: 0.4 | AU34: no | AV34: Inversión | AX34: Otra localidad (Villanueva) | BB34: =IF(A34="RESERVADO",S34,"LIBRE") | BC34: ES76 0078 0035 02 401000 6986
A35: RESERVADO | B35: 44638 | C35: 45412 | E35: 24 | F35: 1 | G35: 4 | H35: A | I35: 4 | J35: 41 | K35: 52 | L35: . | M35: . | N35: 97.99 | O35: 4.61 | P35: 102.6 | Q35: 119.19 | R35: 29.99 | S35: 276600 | T35: 27660 | U35: 304260 | V35: 15213 | W35: 30426 | X35: 15213 | Y35: 22128 | Z35: 221280 | AA35: =AA34+2 | AB35: SERVILIANO VALENCIA DIAZ | AE35: servilianovd@gmail.com | AF35: RAQUEL VIZUETE GONZALEZ | AI35: raquelvizuete@hotmail.com | AJ35: Casados | AK35: C/. Julio Cienfugos Linares 10, Derecha, 3º B de Badajoz | AM35: Hijos | AN35: 47 | AO35: Guardia Civil | AP35: 2100 | AQ35: 47 | AR35: Técnico operación aérea | AS35: 1900 | AT35: 0.8 | AU35: consideraran | AV35: Reposición | AW35: Más grande | AX35: Jardines | BB35: =IF(A35="RESERVADO",S35,"LIBRE") | BC35: ES29 1465 0100 92 1729779798
A36: RESERVADO | B36: 45343 | C36: 45383 | E36: 25 | F36: 1 | G36: 4 | H36: B | I36: 2 | J36: 8 | K36: 12 | L36: . | M36: . | N36: 67.94 | O36: 3.1 | P36: 71.04 | Q36: 82.42 | S36: 189900 | T36: 18990 | U36: 208890 | V36: 6266.7 | W36: 20899 | X36: 10444.5 | Y36: 19359.8 | Z36: 151920 | AA36: =AA35+2 | AB36: ANTONIO SANTIAGO ROMERO | AE36: ansaro7@outlook.es | AF36: ANGELA IGLESIAS DOMINGUEZ | AJ36: Casados | AK36: C/. De la Cebada 7, Cáceres | AN36: 64 | AO36: jubilado | AQ36: 68 | AR36: jubilado | AT36: 0 | AU36: no | AW36: Res. Ocasional | AX36: Cáceres | BB36: =IF(A36="RESERVADO",S36,"LIBRE") | BC36: ES57 0182 0395 8402 0000 5781
A37: RESERVADO | B37: 45336 | C37: 45392 | E37: 26 | F37: 1 | G37: 4 | H37: C | I37: 2 | J37: 65 | K37: 59 | L37: . | M37: . | N37: 64.07 | O37: 2.68 | P37: 66.75 | Q37: 85.32 | S37: 187000 | T37: 18700 | U37: 205700 | V37: 6171 | W37: 20570 | X37: 10285 | Y37: 19074 | Z37: 149600 | AA37: =AA36+2 | AB37: VICENTE MIGUEL SUAREZ MARTIN | AK37: C/. Diputación 5, Monterrubio de la Serena (Badajoz) | AN37: 53 | BB37: =IF(A37="RESERVADO",S37,"LIBRE") | BC37: ES39 2103 7308 9300 1003 9384
A38: RESERVADO | B38: 45319 | C38: 45392 | E38: 27 | F38: 1 | G38: 4 | H38: D | I38: 2 | J38: 53 | K38: 19 | L38: . | M38: . | N38: 67.94 | O38: 3.1 | P38: 71.04 | Q38: 82.42 | S38: 189900 | T38: 18990 | U38: 208890 | V38: 6266.7 | W38: 20889 | X38: 10444.5 | Y38: 19369.8 | Z38: 151920 | AA38: =AA37+2 | AB38: ELENA SANCHEZ RICO | AE38: eschzrico@gmail.com | AF38: …................ | AI38: …........... | AJ38: soltera | AK38: C/. Julia Urdiain Zubelzu 3; bloque 2, 3º D de Badajoz | AM38: no | AO38: policias nac. | BB38: =IF(A38="RESERVADO",S38,"LIBRE") | BC38: ES38 0182 2874 0102 0165 1640
A39: RESERVADO | B39: 44638 | C39: 45405 | E39: 28 | F39: 1 | G39: 5 | H39: A | I39: 4 | J39: 52 | K39: 47 | L39: 49 | M39: . | N39: 97.99 | O39: 0 | P39: 97.99 | Q39: 114.66 | R39: 13.1 | S39: 270415 | T39: 27041.5 | U39: 297456.5 | V39: 0 | W39: 83709.97 | X39: 5250 | Y39: 18750.03 | Z39: 189746.5 | AA39: =AA38+2 | AB39: JOE MANUEL ROMERO MATOS | AE39: jmromeromatos@gmail.com | AF39: ---------------- | AK39: C/. Antonio de Nebrija, 6 A, 2ºB - 06006 Badajoz | AT39: 0.5 | AV39: Reposición | AX39: Jardines | BB39: =IF(A39="RESERVADO",S39,"LIBRE") | BC39: ES40 2100 2194 7602 0026 4280 | BD39: ES44 2100 2194 7302 0034 6320
A40: RESERVADO | C40: 45898 | E40: 29 | F40: 1 | G40: 5 | H40: B | I40: 4 | J40: 19 | K40: 27 | L40: . | M40: . | N40: 113.23 | O40: 3.88 | P40: 117.11 | Q40: 134.23 | R40: 7.8 | S40: 305000 | T40: 30500 | U40: 335500 | V40: 0 | W40: 40260 | X40: 10065 | Y40: 41175 | Z40: 244000 | AA40: =AA39+2 | AB40: SANTIAGO TOLOSA ALVAREZ | AE40: santi.tolosa.alvarez@gmail.com | AJ40: soltero | AK40: C/. Martires 56, 2ºIz - Almendralejo (Badajoz) | BB40: =IF(A40="RESERVADO",S40,"LIBRE") | BC40: ES72 1586 0001 4308 8600 0511
A41: RESERVADO | B41: 44662 | C41: 45411 | E41: 30 | F41: 1 | G41: 5 | H41: C | I41: 4 | J41: 46 | K41: 45 | L41: . | M41: . | N41: 112.01 | O41: 3.88 | P41: 115.89 | Q41: 134.04 | R41: 7.8 | S41: 271400 | T41: 27140 | U41: 298540 | V41: 14927 | W41: 29854 | X41: 14927 | Y41: 21712 | Z41: 217120 | AA41: =AA40+2 | AB41: ANGEL GUTIERREZ ROBLES | AE41: angelgutiez@gmail.com | AF41: DOLORES ALBA GARCIA | AI41: albatecnico@hotmail.com | AJ41: casados en separación de bienes | AK41: C/. Francisco Guerra 16, 2ºD de Badajoz | AM41: si | AN41: 47 | AO41: Ingeniero Sof. | AP41: 2100 | AQ41: 45 | AR41: Funcionaria | AS41: 2200 | AT41: 0.8 | AU41: consideraran | AV41: Reposición | AX41: La Paz | BB41: =IF(A41="RESERVADO",S41,"LIBRE") | BC41: ES36 0049 5953 2621 1620 7535
A42: RESERVADO | C42: 46006 | E42: 31 | F42: 2 | G42: BAJA | H42: A | I42: 5 | J42: 22 | K42: 30 | L42: . | M42: . | N42: 136.79 | O42: 9.46 | P42: 146.25 | Q42: 167.59 | R42: 27.56 | S42: 380000 | T42: 38000 | U42: 418000 | V42: 0 | W42: 62700 | X42: 0 | Y42: 51300 | Z42: 304000 | AA42: =AA41+2 | AB42: MARIA DE LOS ANGELES NAVARRETE GOMEZ | AE42: maria.navarreteg@salud-juntaex.es | BB42: =IF(A42="RESERVADO",S42,"LIBRE")
A43: DISPONIBLE | E43: 32 | F43: 2 | G43: BAJA | H43: B | I43: 4 | J43: 21 | K43: 29 | L43: . | M43: . | N43: 111.63 | O43: 9.64 | P43: 121.27 | Q43: 138.9 | R43: 31.74 | S43: 318200 | T43: 31820 | U43: 350020 | V43: 0 | W43: 38184 | X43: 9546 | Y43: 47730 | Z43: 254560 | AA43: =AA42+2 | BB43: =IF(A43="RESERVADO",S43,"LIBRE")
A44: RESERVADO | B44: 25/19/22 | C44: 45383 | E44: 33 | F44: 2 | G44: BAJA | H44: C | I44: 3 | J44: 33 | K44: 5 | L44: . | M44: . | N44: 95.02 | O44: 5.35 | P44: 100.37 | Q44: 116.06 | R44: 42.63 | S44: 245700 | T44: 24570 | U44: 270270 | V44: 10000 | W44: 20000 | X44: 13513.5 | Y44: 30196.5 | Z44: 196560 | AA44: =AA43+2 | AB44: CLAUDIO BORREGO DOMÍNGUEZ | AE44: claudio.borrego@gmail.com | AF44: MARIA TERESA REAL CARRILLO | AI44: real.maite@gmail.com | AJ44: casados | AK44: C/. Castillo de Olivenza 20 de Badajoz | AM44: no | AN44: 63 | AQ44: 61 | AT44: 0 | AU44: si | AV44: Reposción | AW44: Menor tamaño | AX44: U. Guadiana | BB44: =IF(A44="RESERVADO",S44,"LIBRE") | BC44: ES36 0182 5877 1202 0159 8666
A45: BLOQUEADO | E45: 34 | F45: 2 | G45: BAJA | H45: D | I45: 2 | J45: 20 | K45: 28 | L45: . | M45: . | N45: 59.02 | O45: 4.36 | P45: 63.38 | Q45: 75.23 | R45: 45.06 | S45: 183300 | T45: 18330 | U45: 201630 | V45: 0 | W45: 0 | X45: 0 | Y45: 54990 | Z45: 146640 | AA45: =AA44+2 | BB45: =IF(A45="RESERVADO",S45,"LIBRE")
A46: RESERVADO | B46: 45278 | C46: 45390 | E46: 35 | F46: 2 | G46: BAJA | H46: E | I46: 3 | J46: 6 | K46: 10 | L46: . | M46: . | N46: 93.24 | O46: 5.35 | P46: 98.59 | Q46: 113.72 | R46: 43.11 | S46: 264700 | T46: 26470 | U46: 291170 | V46: 8570.1 | W46: 29117 | X46: 8735 | Y46: 32987.9 | Z46: 211760 | AA46: =AA45+2 | AB46: ANTONIO MURIEL VADILLO | AE46: sirenitomuriel@gmail.com | AJ46: soltero | AK46: C/. Cristobal Colon 5, 2ºC, Plasencia (Cáceres) | AM46: no | AN46: 37 | AO46: Guardia Civil | BB46: =IF(A46="RESERVADO",S46,"LIBRE") | BC46: ES04 0182 1597 6802 0157 8959
A47: RESERVADO | B47: 45191 | C47: 45407 | E47: 36 | F47: 2 | G47: 1 | H47: A | I47: 5 | J47: 61 | K47: 55 | L47: 39 | M47: . | N47: 136.44 | O47: 10.06 | P47: 146.5 | Q47: 168.3 | S47: 376000 | T47: 37600 | U47: 413600 | V47: 12814 | W47: 41360 | X47: 20680 | Y47: 37946 | Z47: 300800 | AA47: =AA46+2 | AB47: CARMEN VICTORIA ROJAS MORENO | AE47: cvrojas@unex.es | AF47: ANTONIO GRANERO VAZQUEZ | AI47: antoniogranerovazquez@outlook.com | AJ47: casada en separación de bienes, compra privativa | AK47: C/. Los Mesones 14 de Calzadilla de los Barros (Badajoz) | AM47: si | AN47: 45 | AO47: Empresario | AQ47: 49 | AR47: Prof. Universidad | AT47: ? | AU47: Si | AV47: Reposicioó | AX47: Rando Norte | BB47: =IF(A47="RESERVADO",S47,"LIBRE") | BC47: ES25 3009 0050 4115 7641 7016
A48: RESERVADO | B48: 44811 | C48: 45401 | E48: 37 | F48: 2 | G48: 1 | H48: B | I48: 4 | J48: 34 | K48: 17 | L48: . | M48: . | N48: 115.06 | O48: 10.26 | P48: 125.32 | Q48: 144.08 | S48: 284900 | T48: 28490 | U48: 313390 | V48: 15669.5 | W48: 31339 | X48: 15669.5 | Y48: 22792 | Z48: 227920 | AA48: =AA47+2 | AB48: JOSE MANUEL ROSON JIMENEZ | AE48: jmrosonjimenez@gmail.com | AF48: MARIA DOLORES RECIO PEREZ | AI48: lolirepe@hotmail.com | AJ48: Casados | AK48: C/. Manuel Godoy 16 -3ºD de Badajoz | AM48: hijos | AN48: 51 | AO48: Funcionario | AP48: 3000 | AQ48: 49 | AR48: Admistrativo | AS48: 1600 | AT48: 0.2 | AU48: si | AV48: Reposción | AW48: Mayor tamaño | AX48: San Fernando | BB48: =IF(A48="RESERVADO",S48,"LIBRE") | BC48: ES03 2100 1982 8702 0034 1549
A49: RESERVADO | B49: 45231 | C49: 45390 | E49: 38 | F49: 2 | G49: 1 | H49: C | I49: 3 | J49: 3 | K49: 3 | L49: . | M49: . | N49: 95.02 | O49: 5.04 | P49: 100.06 | Q49: 116.06 | S49: 229500 | T49: 22950 | U49: 252450 | V49: 7573.5 | W49: 25245 | X49: 12622.5 | Y49: 23409 | Z49: 183600 | AA49: =AA48+2 | AB49: ANTONIO MANUEL PEREZ FERNANDEZ | AE49: ampf7395@gmail.com | AF49: MONICA JIMENEZ MORENO | AI49: mjmoreno753@gmail.com | AJ49: CASADOS | AK49: C/. Castillo de Villagarcia de las Torres 30, de Badajoz | AV49: Para hijos | AX49: Urb.Guadiana | BB49: =IF(A49="RESERVADO",S49,"LIBRE") | BC49: ES98 2100 7515 7613 0043 9391
A50: RESERVADO | B50: 44874 | C50: 45371 | E50: 39 | F50: 2 | G50: 1 | H50: D | I50: 2 | J50: 36 | K50: 39 | L50: . | M50: . | N50: 59.02 | O50: 4.1 | P50: 63.12 | Q50: 75.23 | S50: 159000 | T50: 15900 | U50: 174900 | V50: 8745 | W50: 17490 | X50: 8745 | Y50: 12720 | Z50: 127200 | AA50: =AA49+2 | AB50: FERNANDO LIMA LINEROS | AE50: fernando.lima@siderbalboa.es | AF50: ---------------- | AJ50: soltero | AK50: C/. Republica Argentina 7 - Jerez de los Caballeros (Badajoz) | AM50: no | AN50: 53 | AO50: Ingeniero | AP50: 3800 | AV50: Inversión | AX50: otra población | BB50: =IF(A50="RESERVADO",S50,"LIBRE") | BC50: ES43 0182 3220 6402 0150 3026
A51: RESERVADO | C51: 45509 | E51: 40 | F51: 2 | G51: 1 | H51: E | I51: 3 | J51: 4 | K51: 4 | L51: . | M51: . | N51: 93.24 | O51: 5.04 | P51: 98.28 | Q51: 113.72 | S51: 230900 | T51: 23090 | U51: 253990 | V51: 0 | W51: 27938.9 | X51: 10159.68 | Y51: 31171.42 | Z51: 184720 | AA51: =AA50+2 | AB51: CRISTINA CANCHALES RODRIGUEZ | AE51: barnizadosbadajoz@barnizadosbadajoz.es | AK51: C/. Hermanos Alvarez Sorube 7 de Badajoz | BB51: =IF(A51="RESERVADO",S51,"LIBRE") | BC51: ES09 2100 1845 9601 0013 6568
A52: RESERVADO | B52: 44700 | C52: 45371 | E52: 41 | F52: 2 | G52: 2 | H52: A | I52: 5 | J52: 64 | K52: 58 | L52: 35 | M52: . | N52: 136.46 | O52: 10.71 | P52: 147.17 | Q52: 168.98 | S52: 366000 | T52: 36600 | U52: 402600 | V52: 20130 | W52: 40260 | X52: 20130 | Y52: 29280 | Z52: 292800 | AA52: =AA51+2 | AB52: ALVARO MARTIN DEL POZO | AE52: alvaro_88_4@hotmail.com | AF52: ISABEL LOPEZ MACIAS | AI52: isabel_lm7@hotmail.com | AJ52: casados | AK52: C/. Matilde Tagle =rtiz 24, 6ºB de Badajoz | AM52: hijos | AN52: 34 | AO52: Médico | AP52: 4000 | AQ52: 34 | AR52: Medico | AS52: 4000 | AT52: 0.6 | AU52: no | AV52: reposicion | AW52: más grande | AX52: Jardines | BB52: =IF(A52="RESERVADO",S52,"LIBRE") | BC52: ES88 0049 5953 2920 9509 2365
A53: RESERVADO | B53: 44874 | C53: 45407 | E53: 42 | F53: 2 | G53: 2 | H53: B | I53: 4 | J53: 17 | K53: 24 | L53: . | M53: . | N53: 115.06 | O53: 10.92 | P53: 125.98 | Q53: 144.85 | S53: 286000 | T53: 28600 | U53: 314600 | V53: 15730 | W53: 31460 | X53: 15730 | Y53: 22880 | Z53: 228800 | AA53: =AA52+2 | AB53: ANGEL ANDERICA AREVALO | AE53: angel_anderica@yahoo.es | AF53: PALOMA ESQUETIN LAVADO | AI53: palomaesq@yahoo.es | AJ53: solteros | AK53: C/. Castillo de Hornachos 19 de Badajoz | AM53: hijos | AN53: 47 | AO53: Consultor | AP53: 1400 | AQ53: 45 | AR53: Profesora | AS53: 1300 | AT53: 0.25 | AU53: no | AV53: 1ª vivienda | AW53: consolidacion pareja | AX53: U. Guadiana | BB53: =IF(A53="RESERVADO",S53,"LIBRE") | BC53: ES5402390806740034277723
A54: RESERVADO | C54: 45464 | E54: 43 | F54: 2 | G54: 2 | H54: C | I54: 3 | J54: 7 | K54: 11 | L54: . | M54: . | N54: 95.29 | O54: 5.04 | P54: 100.33 | Q54: 116.06 | S54: 232500 | T54: 23250 | U54: 255750 | V54: 0 | W54: 28132.5 | X54: 12148.03 | Y54: 29469.47 | Z54: 186000 | AA54: =AA53+2 | AB54: MARIA JOSE MERINO PIEDEHIERRO | AE54: mariajosemerino1975@gmail.com | AJ54: divorciada | AK54: C/. Caya 25, Montijo (Badajoz) | BB54: =IF(A54="RESERVADO",S54,"LIBRE") | BC54: ES81 2080 3597 8730 0005 5734
A55: RESERVADO | B55: 44642 | C55: 45426 | E55: 44 | F55: 2 | G55: 2 | H55: D | I55: 2 | J55: 66 | K55: 61 | L55: . | M55: . | N55: 59.02 | O55: 4.1 | P55: 63.12 | Q55: 75.23 | S55: 156700 | T55: 15670 | U55: 172370 | V55: 5237.1 | W55: 12000 | X55: 8618.5 | Y55: 21154.4 | Z55: 125360 | AA55: =AA54+2 | AB55: MARIA DOLORES MERINO GARRIDO | AE55: lola@inmohabitat.es | AF55: ---------------- | AK55: Plaza de la Americas 8 de Badajoz | AT55: 0 | AV55: Inversión | BB55: =IF(A55="RESERVADO",S55,"LIBRE") | BC55: ES38 0049 4640 9825 1609 3727
A56: RESERVADO | B56: 45007 | C56: 45371 | E56: 45 | F56: 2 | G56: 2 | H56: E | I56: 3 | J56: 5 | K56: 8 | L56: . | M56: . | N56: 93.24 | O56: 5.04 | P56: 98.28 | Q56: 113.72 | S56: 225000 | T56: 22500 | U56: 247500 | V56: 7425 | W56: 24750 | X56: 12375 | Y56: 22950 | Z56: 180000 | AA56: =AA55+2 | AB56: JUAN JOSE GALLARDO ARCOS | AE56: jjga0360@gmail.com | AF56: CATALINA MURILLO CARMONA | AJ56: casados | AK56: C/. Labradores 22, bajo - Campanario (Badajoz) | AM56: no | AN56: 63 | AO56: Jubilado | AQ56: 62 | AR56: Profesora | AT56: 0 | AU56: No | AV56: traslado | AX56: Otra localidad | BB56: =IF(A56="RESERVADO",S56,"LIBRE") | BC56: ES06 2085 4575 0103 3004 3050
A57: RESERVADO | B57: 45012 | C57: 45407 | E57: 46 | F57: 2 | G57: 3 | H57: A | I57: 5 | J57: 31 | K57: 6 | L57: . | M57: . | N57: 136.46 | O57: 11.32 | P57: 147.78 | Q57: 166.22 | S57: 351000 | T57: 35100 | U57: 386100 | V57: 11517 | W57: 38590 | X57: 19305 | Y57: 35888 | Z57: 280800 | AA57: =AA56+2 | AB57: MANUEL DURAN GARCIA | AE57: manu.duran84@hotmail.com | AF57: LAURA GASTON RAMOS | AJ57: casados en separación de bienes | AK57: Av. Augusto Vazquez 7, 7ºA de Badajoz | AM57: si | AN57: 39 | AO57: Gerente Gimnasio | AQ57: 35 | AR57: Profesora | AV57: Reposicion | AW57: Mejora | AX57: San Fernando | BB57: =IF(A57="RESERVADO",S57,"LIBRE") | BC57: ES56 0182 1487 5202 0167 6651
A58: RESERVADO | B58: 44874 | C58: 45386 | E58: 47 | F58: 2 | G58: 3 | H58: B | I58: 4 | J58: 37 | K58: 40 | L58: . | M58: . | N58: 115.06 | O58: 11.54 | P58: 126.6 | Q58: 141.97 | S58: 294000 | T58: 29400 | U58: 323400 | V58: 16170 | W58: 32340 | X58: 16170 | Y58: 23520 | Z58: 235200 | AA58: =AA57+2 | AB58: ANGEL CARRION AGUILERA | AE58: angelcarrion13@gmail.com | AF58: RAQUEL MURIEL RODRIGUEZ | AI58: raquelmriel13@gmail.com | AJ58: casados | AK58: C/. Castillo de Feria 11 de Badajoz | AM58: no | AN58: 60 | AO58: Profesor | AP58: 2200 | AQ58: 60 | AR58: Profesora | AS58: 2200 | AT58: 0.2 | AU58: si | AV58: reposición | AW58: vende unifamiliar | AX58: U. Guadiana | BB58: =IF(A58="RESERVADO",S58,"LIBRE") | BC58: ES57 1465 0100 9117 1838 5529
A59: RESERVADO | B59: 44648 | C59: 45386 | E59: 48 | F59: 2 | G59: 3 | H59: C | I59: 3 | J59: 18 | K59: 26 | L59: . | M59: . | N59: 95.29 | O59: 5.04 | P59: 100.33 | Q59: 116.06 | S59: 232000 | T59: 23200 | U59: 255200 | V59: 12760 | W59: 20000 | X59: 18280 | Y59: 18560 | Z59: 185600 | AA59: =AA58+2 | AB59: JOSE DIEGO HIDALGO DOMINGUEZ | AE59: josediegoj75@gmail.com | AF59: YOLANDA ESQUINAS RAMOS | AI59: luz_de_elendil@hotmail.com | AJ59: casados | AK59: C/. Julia Urdiain Zubelzu 8; bloque 3, 1º E de Badajoz | AM59: hijos | AN59: 47 | AO59: Banca | AP59: 2200 | AQ59: 43 | AR59: Mercadona | AS59: 1100 | AT59: 0.8 | AU59: no | AV59: Reposición | AW59: de 2 a 3 | AX59: Jardines | BB59: =IF(A59="RESERVADO",S59,"LIBRE") | BC59: ES61 2100 1209 6102 0009 4376
A60: RESERVADO | B60: 44642 | C60: 45426 | E60: 49 | F60: 2 | G60: 3 | H60: D | I60: 2 | J60: 67 | K60: 62 | L60: . | M60: . | N60: 59.02 | O60: 4.1 | P60: 63.12 | Q60: 75.23 | S60: 158700 | T60: 15870 | U60: 174570 | V60: 5237.1 | W60: 12250 | X60: 8728.5 | Y60: 21394.4 | Z60: 126960 | AA60: =AA59+2 | AB60: ALBERTO GARCIA SARDIÑA | AE60: alberto@inmohabitat.es | AF60: ---------------- | AK60: Plaza de la Americas 8 de Badajoz | AT60: 0 | AV60: Inversión | BB60: =IF(A60="RESERVADO",S60,"LIBRE") | BC60: ES72 0049 4640 9726 1037 2411
A61: RESERVADO | C61: 45415 | E61: 50 | F61: 2 | G61: 3 | H61: E | I61: 3 | J61: 23 | K61: 31 | L61: . | M61: . | N61: 93.24 | O61: 5.04 | P61: 98.28 | Q61: 113.72 | S61: 234000 | T61: 23400 | U61: 257400 | V61: 7722 | W61: 27740 | X61: 12870 | Y61: 21868 | Z61: 187200 | AA61: =AA60+2 | AB61: FELIPA PEREZ CORRALES | AE61: perezcorrales_@hotmail.com | AK61: C/. Madame Curie 209, 1ºB de Cáceres | AM61: no | AN61: 63 | AO61: Funcionario | AP61: 1500 | AT61: 0 | AU61: no | AV61: Reposicion | AX61: Otra localidad (Cáceres) | BB61: 239700 | BC61: ES60 3009 0110 9628 2475 4325
A62: RESERVADO | B62: 44641 | C62: 45393 | E62: 51 | F62: 3 | G62: BAJA | H62: A | I62: 3 | J62: 1 | K62: 1 | L62: . | M62: . | N62: 89.76 | O62: 7.26 | P62: 97.02 | Q62: 112.41 | R62: 20.32 | S62: 245400 | T62: 24540 | U62: 269940 | V62: 13497 | W62: 26994 | X62: 13497 | Y62: 19632 | Z62: 196320 | AA62: =AA61+2 | AB62: RICARDO ANTONIO SANCHEZ HERNANDEZ | AE62: rschzrico@gmail.com | AF62: JUANA RICO ALBERCA | AI62: jricoalberca@gmail.com | AJ62: casados | AK62: Calle Julia Urdiain Zubelzu 3, 3ºD de Badajoz | AM62: hijos | AN62: 69 | AO62: Jubilado | AP62: 1200 | AQ62: 58 | AR62: funcionaria | AS62: 1600 | AT62: 0 | AU62: no | AV62: Para hijos | AW62: Cercania | AX62: Jardines | BB62: =IF(A62="RESERVADO",S62,"LIBRE") | BC62: ES78 0182 5877 1302 0160 7173
A63: DISPONIBLE | E63: 52 | F63: 3 | G63: BAJA | H63: B | I63: 4 | J63: 2 | K63: 2 | L63: . | M63: . | N63: 100.96 | O63: 9.57 | P63: 110.53 | Q63: 128.61 | R63: 19.64 | S63: 315000 | T63: 31500 | U63: 346500 | V63: 0 | W63: 41580 | X63: 9450 | Y63: 43470 | Z63: 252000 | AA63: =AA62+2 | BB63: =IF(A63="RESERVADO",S63,"LIBRE")
A64: RESERVADO | B64: 44699 | C64: 45383 | E64: 53 | F64: 3 | G64: BAJA | H64: C | I64: 4 | J64: 27 | K64: 36 | L64: 55 | M64: . | N64: 99.79 | O64: 9.15 | P64: 108.94 | Q64: 126.81 | R64: 56.41 | S64: 307200 | T64: 30720 | U64: 337920 | V64: 16896 | W64: 33792 | X64: 16896 | Y64: 24576 | Z64: 245760 | AA64: =AA63+2 | AB64: FELIX ARTURO MERA GALLARDO | AE64: felixmeragallardo@gmail.com | AF64: ROSA MARIA GIJON CAPOTE | AI64: rmgcapote@gmail.com | AJ64: casados | AK64: C/. Castillo Puebla de Alcocer, 43 de Badajoz | AM64: hijos | AN64: 58 | AO64: Funcionario | AP64: 1400 | AQ64: 57 | AR64: Comercial | AS64: 3000 | AT64: 0 | AU64: si | AV64: Reposición | AW64: cambio unifamiliar | AY64: queria 4ª A portal 1 | BB64: =IF(A64="RESERVADO",S64,"LIBRE") | BC64: ES05 2103 7120 1700 3009 3611 | BD64: ES05 2103 7120 17 0030093611
A65: RESERVADO | B65: 44699 | C65: 45383 | E65: 54 | F65: 3 | G65: BAJA | H65: D | I65: 3 | J65: 68 | K65: 63 | L65: . | M65: . | N65: 85.85 | O65: 7.51 | P65: 93.36 | Q65: 108.47 | R65: 48.01 | S65: 267900 | T65: 26790 | U65: 294690 | V65: 14734.5 | W65: 29469 | X65: 14734.5 | Y65: 21432 | Z65: 214320 | AA65: =AA64+2 | AB65: MANUEL LOPEZ LEON | AE65: lololopez31@gmail.com | AF65: CRISTINA POLO FERNANDEZ | AI65: cristinapolo83@gmail.com | AJ65: casados | AK65: C/. General Cuesta 22, 3A de Badajoz | AM65: hijos | AN65: 39 | AO65: Ingeniero | AP65: 2200 | AQ65: 39 | AR65: Prof. Universidad | AS65: 2000 | AT65: 0.5 | AU65: si | AV65: Reposción | AW65: Cercania trabajo | AX65: Cerro Gordo | BB65: =IF(A65="RESERVADO",S65,"LIBRE") | BC65: ES65 0049 6147 6828 1003 9553
A66: RESERVADO | B66: 44894 | C66: 45383 | E66: 55 | F66: 3 | G66: 1 | H66: A | I66: 3 | J66: 28 | K66: 37 | L66: . | M66: . | N66: 91.2 | O66: 7.73 | P66: 98.93 | Q66: 115.85 | S66: 231100 | T66: 23110 | U66: 254210 | V66: 7626.3 | W66: 25421 | X66: 12710.5 | Y66: 23572.2 | Z66: 184880 | AA66: =AA65+2 | AB66: ESPERANZA FERMOSELLE INFANTE | AE66: espferinf@gmail.com | AF66: ANTONIO FLORIAN RAMIREZ ORDOÑEZ | AI66: aframirezo01@educarex.es | AJ66: solteros | AK66: Av- Carolina Coronado 9, 4º -2ªpuerta de Badajoz | AM66: no | AN66: 30 | AO66: Profesora | AP66: 1800 | AQ66: 34 | AR66: Profesora | AS66: 1800 | AT66: 0.8 | AU66: no | AV66: 1ª Vivienda | AX66: San Fernando | BB66: =IF(A66="RESERVADO",S66,"LIBRE") | BC66: ES17 0182 1487 5302 0175 1606
A67: RESERVADO | C67: 45398 | E67: 56 | F67: 3 | G67: 1 | H67: B | I67: 4 | J67: 72 | K67: 67 | L67: . | M67: . | N67: 104.92 | O67: 9.6 | P67: 114.52 | Q67: 133.71 | S67: 304400 | T67: 30440 | U67: 334840 | V67: 0 | W67: 36777.74 | X67: 16742 | Y67: 37800.26 | Z67: 243520 | AA67: =AA66+2 | AB67: MIGUEL SANCHEZ SANCHEZ | AE67: msanchez9337@gmail.com | AF67: MARTA AGUILAR GONZALEZ | AI67: marta.aguilargonzalez@gmail.com | AJ67: solteros | AK67: Calle Teresa Istúriz 2, 2°A, 06008 Badajoz | BB67: =IF(A67="RESERVADO",S67,"LIBRE")
A68: RESERVADO | C68: 45566 | E68: 57 | F68: 3 | G68: 1 | H68: C | I68: 4 | J68: 30 | K68: 34 | L68: 47 | M68: . | N68: 99.79 | O68: 9.23 | P68: 109.02 | Q68: 127.31 | S68: 313000 | T68: 31300 | U68: 344300 | V68: 0 | W68: 37873 | X68: 30987 | Y68: 25040 | Z68: 250400 | AA68: =AA67+2 | AB68: PABLO JESUS BARAHONA DIESTRE | AE68: pablojesusbarahonadiestre@gmail.com | AF68: MARIA TERESA GARCIA GARCIA | AI68: teregg86@hotmail.com | AJ68: solteros | AK68: C/. Hernando de Soto 1, 3ºA de Badajoz | BB68: =IF(A68="RESERVADO",S68,"LIBRE") | BC68: ES40 0049 7060 7827 1001 1307
A69: RESERVADO | C69: 45590 | E69: 58 | F69: 3 | G69: 1 | H69: D | I69: 3 | J69: 32 | K69: 41 | L69: . | M69: . | N69: 85.85 | O69: 7.07 | P69: 92.92 | Q69: 108.47 | S69: 239500 | T69: 23950 | U69: 263450 | V69: 0 | W69: 15000 | X69: 14000 | Y69: 42850 | Z69: 191600 | AA69: =AA68+2 | AB69: ISABEL PEREZ CARVAJAL | AE69: isabelperezcarvajal@gmail.com | AF69: …............................................ | AI69: …................ | AJ69: divorciada | AK69: C/. De los Generosos 45, Gevora (Badajoz) | AM69: no | AN69: 27 | AO69: Medico | BB69: =IF(A69="RESERVADO",S69,"LIBRE") | BC69: ES50 3009 0088 2921 8850 5818
A70: RESERVADO | C70: 45839 | E70: 59 | F70: 3 | G70: 2 | H70: A | I70: 3 | J70: 29 | K70: 38 | L70: . | M70: . | N70: 91.13 | O70: 8.22 | P70: 99.35 | Q70: 116.44 | S70: 262000 | T70: 26200 | U70: 288200 | V70: 0 | W70: 34584 | X70: 8646 | Y70: 35370 | Z70: 209600 | AA70: =AA69+2 | AB70: RICARDO ANTONIO SANCHEZ RICO | AE70: sanchez.romero.2023@gmail.com | AF70: MARIA MORENO ROMERO | AJ70: casados en separacion de bienes | AK70: Antonio de Nebrija 6A, 3ºC de Badajoz | BB70: =IF(A70="RESERVADO",S70,"LIBRE") | BC70: ES31 0182 1294 1002 0243 9783
A71: RESERVADO | B71: 44916 | C71: 45390 | E71: 60 | F71: 3 | G71: 2 | H71: B | I71: 4 | J71: 25 | K71: 33 | L71: . | M71: . | N71: 104.43 | O71: 8.87 | P71: 113.3 | Q71: 131.83 | R71: 13.59 | S71: 286600 | T71: 28660 | U71: 315260 | V71: 9457.8 | W71: 158526 | X71: 15763 | Y71: 0 | Z71: 131513.2 | AA71: =AA70+2 | AB71: JOHAN MAURICIO QUINTERO PLAZA | AE71: johanq88@gmail.com | AF71: LIDIA MORENO HERREZUELO | AI71: lidiamorenoh@yahoo.es | AJ71: casados en separación de bienes | AK71: C/. Nuño de la Cueva 12 de Badajoz | AM71: no | AN71: 34 | AO71: Ing. Electrico | AQ71: 36 | AT71: 0.8 | AV71: Reposición | AW71: Traslado | AX71: Otra localidad | AY71: quieres un 4 grande | BA71: POSIBILIADAD 5 2ºfASE | BB71: =IF(A71="RESERVADO",S71,"LIBRE") | BC71: ES59 1465 0100 9917 3352 1951
A72: RESERVADO | C72: 45460 | E72: 61 | F72: 3 | G72: 2 | H72: C | I72: 4 | J72: 24 | K72: 32 | L72: . | M72: . | N72: 99.79 | O72: 9.23 | P72: 109.02 | Q72: 127.31 | S72: 295000 | T72: 29500 | U72: 324500 | V72: 0 | W72: 35695 | X72: 15413.75 | Y72: 37391.25 | Z72: 236000 | AA72: =AA71+2 | AB72: ALVARO JOSE NAVARRETE POZUECO | AE72: alvaronavarretedev@gmail.com | AF72: ANA CALDERON FERNANDEZ-SALGUERO | AI72: anacfs03@gmail.com | AJ72: solteros | AK72: C/. Arco Agüero 19, 2ºD de Badajoz | BB72: =IF(A72="RESERVADO",S72,"LIBRE") | BC72: ES41 0049 5953 2326 1619 3801
A73: RESERVADO | C73: 45846 | E73: 62 | F73: 3 | G73: 2 | H73: D | I73: 3 | J73: 63 | K73: 57 | L73: . | M73: . | N73: 86.77 | O73: 7.07 | P73: 93.84 | Q73: 108.47 | S73: 258000 | T73: 25800 | U73: 283800 | V73: 0 | W73: 34056 | X73: 8514 | Y73: 34830 | Z73: 206400 | AA73: =AA72+2 | AB73: RAUL AVILA GARCIA | AE73: rayul_mont_@hotmail.com | AF73: MERCEDES GRAJERA GOMEZ | AJ73: casados en separación de bienes | AK73: C/. Democracia 27 - Montijo (Badajoz) | BB73: =IF(A73="RESERVADO",S73,"LIBRE") | BC73: ES82 2100 3752 2122 0025 0040
A74: RESERVADO | B74: 44638 | C74: 45386 | E74: 63 | F74: 3 | G74: 3 | H74: A | I74: 3 | J74: 71 | K74: 66 | L74: 56 | M74: . | N74: 91.13 | O74: 8.69 | P74: 99.82 | Q74: 114.25 | S74: 251700 | T74: 25170 | U74: 276870 | V74: 13843.5 | W74: 27687 | X74: 13843.5 | Y74: 20136 | Z74: 201360 | AA74: =AA73+2 | AB74: ALBERTO FERNANDEZ PARRAL | AE74: afp1982@hotmail.com | AF74: ESTHER RODRIGUEZ GORDO | AI74: esther.rg82@gmail.com | AJ74: casados | AK74: Calle Julio Cienfuegos Linares n° 15, 1° B. | AM74: hijos | AN74: 40 | AO74: Admnistrativo | AP74: 1200 | AQ74: 40 | AR74: Profesora | AS74: 2000 | AT74: 80 | AU74: no | AV74: 1ª Vivienda | AX74: Av.Elvas/Jardines | BB74: =IF(A74="RESERVADO",S74,"LIBRE") | BC74: ES69 1465 0100 9717 1924 2693
A75: RESERVADO | B75: 45310 | C75: 45411 | E75: 64 | F75: 3 | G75: 3 | H75: B | I75: 4 | J75: 70 | K75: 65 | L75: . | M75: . | N75: 104.43 | O75: 8.56 | P75: 112.99 | Q75: 131.83 | S75: 303400 | T75: 30340 | U75: 333740 | V75: 10012.2 | W75: 33374 | X75: 10012.2 | Y75: 37621.6 | Z75: 242720 | AA75: =AA74+2 | AB75: MARIA GARRIDO ALVAREZ | AE75: m.garrido84@hotmail.com | AF75: JAVIER ESPINO PALMA | AJ75: CASADOS | AK75: Av. Sinforiano Madroñero 32, 7º A de Badajoz | BB75: =IF(A75="RESERVADO",S75,"LIBRE") | BC75: ES69 0182 1508 5202 0159 9028
A76: RESERVADO | B76: 44720 | C76: 45383 | E76: 65 | F76: 3 | G76: 3 | H76: C | I76: 4 | J76: 69 | K76: 64 | L76: . | M76: . | N76: 99.79 | O76: 9.23 | P76: 109.02 | Q76: 127.31 | S76: 275400 | T76: 27540 | U76: 302940 | V76: 15147 | W76: 30294 | X76: 15147 | Y76: 22032 | Z76: 220320 | AA76: =AA75+2 | AB76: AURELIO COLLADO BARRAGAN | AE76: aureliocolladobarragan@yahoo.es | AF76: MARIA ELENA AREVALO MUÑOZ | AI76: elena.arevalo67@yahoo.es | AJ76: casados | AK76: C/. Castillo de Magacela, 24 de Badajoz | AM76: no | AN76: 57 | AO76: Administrativo | AQ76: 55 | AR76: Funcionario | AT76: n/d | AV76: Reposición | AX76: U. Guadiana | BB76: =IF(A76="RESERVADO",S76,"LIBRE") | BC76: ES43 0128 0060 5501 0307 8574
A77: RESERVADO | C77: 45422 | E77: 66 | F77: 3 | G77: 3 | H77: D | I77: 3 | J77: 26 | K77: 35 | L77: . | M77: . | N77: 86.77 | O77: 7.07 | P77: 93.84 | Q77: 108.47 | S77: 243500 | T77: 24350 | U77: 267850 | V77: 0 | W77: 29463.5 | X77: 13392.6 | Y77: 30193.9 | Z77: 194800 | AB77: EMILIO BENITEZ ACEDO | AE77: emilioj_22@hotmail.com | AF77: MARIA ALMEIDA GONZALEZ | AI77: Malmeidag91@gmail.com | AJ77: solteros | AK77: C/. Pintor Barjola 29, 2ºB de Badajoz | BB77: =IF(A77="RESERVADO",S77,"LIBRE") | BC77: ES23 0182 2874 0602 0161 3253
Q78: Montante origen | S78: 15529500

Sheet MEJORAS
B1: IMPORTES MEJORAS
B6: Nº Orden | C6: VIVIENDA | F6: TITULAR 1 | G6: PRECIO | J6: FORMA DE PAGO ESTANDAR (IVA inlcuido) | N6: PORCELANICO | O6: IVA PORCELÁNICO | P6: TOTAL PORCELÁNICO | Q6: TOTAL IMPORTE MEJORAS (SIN IVA) | R6: TOTAL IMPORTE MEJORAS (CON IVA)
C7: PORTAL | D7: PLANTA | E7: LETRA | G7: Neto | H7: IVA | I7: TOTAL 1 | J7: PAGO INICIAL | K7: Resto | L7: nº pagos | M7: importe individual pagos
B9: 1 | C9: 1 | D9: BAJA | E9: A | F9: =+'SITUACION COMERCIAL'!AB12 | G9: 5625 | H9: =+G9*0.1 | I9: =+H9+G9 | J9: =+I9-K9 | K9: =+M9*L9 | L9: 19 | M9: 195.39 | N9: =+'TOTAL OPERACION'!R10 | O9: =N9*0.1 | P9: =N9+O9 | Q9: =N9+G9 | R9: =P9+I9
B10: =+B9+1 | C10: 1 | D10: BAJA | E10: B | F10: =+'SITUACION COMERCIAL'!AB13 | G10: 1775 | H10: =+G10*0.1 | I10: =+H10+G10 | J10: =+I10-K10 | K10: =+M10*L10 | L10: 19 | M10: 61.65 | N10: =+'TOTAL OPERACION'!R11 | O10: =N10*0.1 | P10: =N10+O10 | Q10: =N10+G10 | R10: =P10+I10
B11: 3 | C11: 1 | D11: BAJA | E11: C | F11: =+'SITUACION COMERCIAL'!AB14 | H11: =+G11*0.1 | I11: =+H11+G11 | L11: 20 | N11: =+'TOTAL OPERACION'!R12 | O11: =N11*0.1 | P11: =N11+O11 | Q11: =N11+G11 | R11: =P11+I11
B12: =+B11+1 | C12: 1 | D12: BAJA | E12: D | F12: =+'SITUACION COMERCIAL'!AB15 | G12: 1250 | H12: =+G12*0.1 | I12: =+H12+G12 | J12: 550.06 | K12: =+L12*M12 | L12: 18 | M12: 45.83 | N12: =+'TOTAL OPERACION'!R13 | O12: =N12*0.1 | P12: =N12+O12 | Q12: =N12+G12 | R12: =P12+I12
B13: =+B12+1 | C13: 1 | D13: BAJA | E13: E | F13: =+'SITUACION COMERCIAL'!AB28 | H13: =+G13*0.1 | I13: =+H13+G13 | L13: 20 | N13: =+'TOTAL OPERACION'!R14 | O13: =N13*0.1 | P13: =N13+O13 | Q13: =N13+G13 | R13: =P13+I13
B14: =+B13+1 | C14: 1 | D14: 1 | E14: A | F14: =+'SITUACION COMERCIAL'!AB17 | G14: 2465 | H14: =+G14*0.1 | I14: =+H14+G14 | J14: =+I14-K14 | K14: =+M14*L14 | L14: 19 | M14: 85.62 | N14: =+'TOTAL OPERACION'!R15 | O14: =N14*0.1 | P14: =N14+O14 | Q14: =N14+G14 | R14: =P14+I14
B15: =+B14+1 | C15: 1 | D15: 1 | E15: B | F15: =+'SITUACION COMERCIAL'!AB18 | H15: =+G15*0.1 | I15: =+H15+G15 | L15: 20 | N15: =+'TOTAL OPERACION'!R16 | O15: =N15*0.1 | P15: =N15+O15 | Q15: =N15+G15 | R15: =P15+I15
B16: =+B15+1 | C16: 1 | D16: 1 | E16: C | F16: =+'SITUACION COMERCIAL'!AB19 | H16: =+G16*0.1 | I16: =+H16+G16 | L16: 20 | N16: =+'TOTAL OPERACION'!R17 | O16: =N16*0.1 | P16: =N16+O16 | Q16: =N16+G16 | R16: =P16+I16
B17: =+B16+1 | C17: 1 | D17: 1 | E17: D | F17: =+'SITUACION COMERCIAL'!AB20 | H17: =+G17*0.1 | I17: =+H17+G17 | L17: 20 | N17: =+'TOTAL OPERACION'!R18 | O17: =N17*0.1 | P17: =N17+O17 | Q17: =N17+G17 | R17: =P17+I17
B18: =+B17+1 | C18: 1 | D18: 1 | E18: E | F18: =+'SITUACION COMERCIAL'!AB21 | G18: 685 | H18: =+G18*0.1 | I18: =+H18+G18 | J18: 753.5 | L18: 20 | N18: =+'TOTAL OPERACION'!R19 | O18: =N18*0.1 | P18: =N18+O18 | Q18: =N18+G18 | R18: =P18+I18
B19: =+B18+1 | C19: 1 | D19: 1 | E19: F | F19: =+'SITUACION COMERCIAL'!AB22 | H19: =+G19*0.1 | I19: =+H19+G19 | L19: 20 | N19: =+'TOTAL OPERACION'!R20 | O19: =N19*0.1 | P19: =N19+O19 | Q19: =N19+G19 | R19: =P19+I19
B20: =+B19+1 | C20: 1 | D20: 2 | E20: A | F20: =+'SITUACION COMERCIAL'!AB23 | G20: =2015+90 | H20: =+G20*0.1 | I20: =+H20+G20 | J20: 886.5 | K20: =+M20*L20 | L20: 19 | M20: 75.21 | N20: =+'TOTAL OPERACION'!R21 | O20: =N20*0.1 | P20: =N20+O20 | Q20: =N20+G20 | R20: =P20+I20
B21: =+B20+1 | C21: 1 | D21: 2 | E21: B | F21: =+'SITUACION COMERCIAL'!AB24 | G21: 2610 | H21: =+G21*0.1 | I21: =+H21+G21 | J21: 1148.46 | K21: =+M21*L21 | L21: 19 | M21: =1722.54/19 | N21: =+'TOTAL OPERACION'!R22 | O21: =N21*0.1 | P21: =N21+O21 | Q21: =N21+G21 | R21: =P21+I21
B22: =+B21+1 | C22: 1 | D22: 2 | E22: C | F22: =+'SITUACION COMERCIAL'!AB25 | G22: 495 | H22: =+G22*0.1 | I22: =+H22+G22 | J22: =+I22 | L22: 20 | N22: =+'TOTAL OPERACION'!R23 | O22: =N22*0.1 | P22: =N22+O22 | Q22: =N22+G22 | R22: =P22+I22
B23: =+B22+1 | C23: 1 | D23: 2 | E23: D | F23: =+'SITUACION COMERCIAL'!AB26 | G23: 1185 | H23: =+G23*0.1 | I23: =+H23+G23 | J23: 524.5 | K23: =+M23*L23 | L23: 19 | M23: 41 | N23: =+'TOTAL OPERACION'!R24 | O23: =N23*0.1 | P23: =N23+O23 | Q23: =N23+G23 | R23: =P23+I23
B24: =+B23+1 | C24: 1 | D24: 2 | E24: E | F24: =+'SITUACION COMERCIAL'!AB27 | G24: 1250 | H24: =+G24*0.1 | I24: =+H24+G24 | J24: 500 | K24: =+M24*L24+0.02 | L24: 18 | M24: 48.61 | N24: =+'TOTAL OPERACION'!R25 | O24: =N24*0.1 | P24: =N24+O24 | Q24: =N24+G24 | R24: =P24+I24
B25: =+B24+1 | C25: 1 | D25: 2 | E25: F | F25: =+'SITUACION COMERCIAL'!#REF! | H25: =+G25*0.1 | I25: =+H25+G25 | L25: 20 | N25: =+'TOTAL OPERACION'!R26 | O25: =N25*0.1 | P25: =N25+O25 | Q25: =N25+G25 | R25: =P25+I25
B26: =+B25+1 | C26: 1 | D26: 3 | E26: A | F26: =+'SITUACION COMERCIAL'!AB29 | G26: 3800 | H26: =+G26*0.1 | I26: =+H26+G26 | J26: 1672 | K26: =+M26*L26 | L26: 19 | M26: 132 | N26: =+'TOTAL OPERACION'!R27 | O26: =N26*0.1 | P26: =N26+O26 | Q26: =N26+G26 | R26: =P26+I26
B27: =+B26+1 | C27: 1 | D27: 3 | E27: B | F27: =+'SITUACION COMERCIAL'!AB30 | G27: 1880 | H27: =+G27*0.1 | I27: =+H27+G27 | J27: 827.3 | L27: 19 | M27: 65.3 | N27: =+'TOTAL OPERACION'!R28 | O27: =N27*0.1 | P27: =N27+O27 | Q27: =N27+G27 | R27: =P27+I27
B28: =+B27+1 | C28: 1 | D28: 3 | E28: C | F28: =+'SITUACION COMERCIAL'!AB31 | G28: 0 | H28: =+G28*0.1 | I28: =+H28+G28 | L28: 20 | N28: =+'TOTAL OPERACION'!R29 | O28: =N28*0.1 | P28: =N28+O28 | Q28: =N28+G28 | R28: =P28+I28
B29: =+B28+1 | C29: 1 | D29: 3 | E29: D | F29: =+'SITUACION COMERCIAL'!AB32 | G29: 0 | H29: =+G29*0.1 | I29: =+H29+G29 | L29: 20 | N29: =+'TOTAL OPERACION'!R30 | O29: =N29*0.1 | P29: =N29+O29 | Q29: =N29+G29 | R29: =P29+I29
B30: =+B29+1 | C30: 1 | D30: 3 | E30: E | F30: =+'SITUACION COMERCIAL'!AB33 | G30: 1540 | H30: =+G30*0.1 | I30: =+H30+G30 | J30: 677.72 | L30: 18 | M30: 56.46 | N30: =+'TOTAL OPERACION'!R31 | O30: =N30*0.1 | P30: =N30+O30 | Q30: =N30+G30 | R30: =P30+I30
B31: =+B30+1 | C31: 1 | D31: 3 | E31: F | F31: =+'SITUACION COMERCIAL'!AB34 | G31: 1125 | H31: =+G31*0.1 | I31: =+H31+G31 | J31: 495 | K31: =+M31*L31 | L31: 18 | M31: 41.25 | N31: =+'TOTAL OPERACION'!R32 | O31: =N31*0.1 | P31: =N31+O31 | Q31: =N31+G31 | R31: =P31+I31
B32: =+B31+1 | C32: 1 | D32: 4 | E32: A | F32: =+'SITUACION COMERCIAL'!AB35 | G32: 3345 | H32: =+G32*0.1 | I32: =+H32+G32 | J32: 735.9 | K32: =+M32*L32 | L32: 15 | M32: 196.24 | N32: =+'TOTAL OPERACION'!R33 | O32: =N32*0.1 | P32: =N32+O32 | Q32: =N32+G32 | R32: =P32+I32
B33: =+B32+1 | C33: 1 | D33: 4 | E33: B | F33: =+'SITUACION COMERCIAL'!AB36 | G33: 1385 | H33: =+G33*0.1 | I33: =+H33+G33 | J33: 609.4 | K33: =+M33*L33 | L33: 19 | M33: 48.11 | N33: =+'TOTAL OPERACION'!R34 | O33: =N33*0.1 | P33: =N33+O33 | Q33: =N33+G33 | R33: =P33+I33
B34: =+B33+1 | C34: 1 | D34: 4 | E34: C | F34: =+'SITUACION COMERCIAL'!AB37 | G34: 1250 | H34: =+G34*0.1 | I34: =+H34+G34 | J34: 500 | K34: 875 | L34: 18 | M34: 48.61 | N34: =+'TOTAL OPERACION'!R35 | O34: =N34*0.1 | P34: =N34+O34 | Q34: =N34+G34 | R34: =P34+I34
B35: =+B34+1 | C35: 1 | D35: 4 | E35: D | F35: =+'SITUACION COMERCIAL'!AB38 | G35: 1070 | H35: =+G35*0.1 | I35: =+H35+G35 | J35: 470.96 | K35: =+L35*M35 | L35: 19 | M35: 37.16 | N35: =+'TOTAL OPERACION'!R36 | O35: =N35*0.1 | P35: =N35+O35 | Q35: =N35+G35 | R35: =P35+I35
B36: =+B35+1 | C36: 1 | D36: 5 | E36: A | F36: =+'SITUACION COMERCIAL'!AB39 | G36: 2715 | H36: =+G36*0.1 | I36: =+H36+G36 | J36: 2986.5 | L36: 20 | N36: =+'TOTAL OPERACION'!R37 | O36: =N36*0.1 | P36: =N36+O36 | Q36: =N36+G36 | R36: =P36+I36
B37: =+B36+1 | C37: 1 | D37: 5 | E37: B | F37: =+'SITUACION COMERCIAL'!AB40 | H37: =+G37*0.1 | I37: =+H37+G37 | L37: 20 | N37: =+'TOTAL OPERACION'!R38 | O37: =N37*0.1 | P37: =N37+O37 | Q37: =N37+G37 | R37: =P37+I37
B38: =+B37+1 | C38: 1 | D38: 5 | E38: C | F38: =+'SITUACION COMERCIAL'!AB41 | G38: 0 | H38: =+G38*0.1 | I38: =+H38+G38 | L38: 20 | N38: =+'TOTAL OPERACION'!R39 | O38: =N38*0.1 | P38: =N38+O38 | Q38: =N38+G38 | R38: =P38+I38
B39: =+B38+1 | C39: 2 | D39: BAJA | E39: A | F39: =+'SITUACION COMERCIAL'!AB42 | H39: =+G39*0.1 | I39: =+H39+G39 | L39: 20 | N39: =+'TOTAL OPERACION'!R40 | O39: =N39*0.1 | P39: =N39+O39 | Q39: =N39+G39 | R39: =P39+I39
B40: =+B39+1 | C40: 2 | D40: BAJA | E40: B | F40: =+'SITUACION COMERCIAL'!AB43 | H40: =+G40*0.1 | I40: =+H40+G40 | L40: 20 | N40: =+'TOTAL OPERACION'!R41 | O40: =N40*0.1 | P40: =N40+O40 | Q40: =N40+G40 | R40: =P40+I40
B41: =+B40+1 | C41: 2 | D41: BAJA | E41: C | F41: =+'SITUACION COMERCIAL'!AB44 | G41: 3280 | H41: =+G41*0.1 | I41: =+H41+G41 | J41: =+I41*0.4-0.06 | K41: =+M41*L41 | L41: 19 | M41: 113.94 | N41: =+'TOTAL OPERACION'!R42 | O41: =N41*0.1 | P41: =N41+O41 | Q41: =N41+G41 | R41: =P41+I41
B42: =+B41+1 | C42: 2 | D42: BAJA | E42: D | F42: =+'SITUACION COMERCIAL'!AB45 | H42: =+G42*0.1 | I42: =+H42+G42 | L42: 20 | N42: =+'TOTAL OPERACION'!R43 | O42: =N42*0.1 | P42: =N42+O42 | Q42: =N42+G42 | R42: =P42+I42
B43: =+B42+1 | C43: 2 | D43: BAJA | E43: E | F43: =+'SITUACION COMERCIAL'!AB46 | G43: 875 | H43: =+G43*0.1 | I43: =+H43+G43 | J43: =+I43*0.4-0.1 | K43: =+M43*19 | L43: 19 | M43: 30.4 | N43: =+'TOTAL OPERACION'!R44 | O43: =N43*0.1 | P43: =N43+O43 | Q43: =N43+G43 | R43: =P43+I43
B44: =+B43+1 | C44: 2 | D44: 1 | E44: A | F44: =+'SITUACION COMERCIAL'!AB47 | G44: 0 | H44: =+G44*0.1 | I44: =+H44+G44 | L44: 20 | N44: =+'TOTAL OPERACION'!R45 | O44: =N44*0.1 | P44: =N44+O44 | Q44: =N44+G44 | R44: =P44+I44
B45: =+B44+1 | C45: 2 | D45: 1 | E45: B | F45: =+'SITUACION COMERCIAL'!AB48 | G45: 1855 | H45: =+G45*0.1 | I45: =+H45+G45 | J45: =+I45*0.4+0.13 | K45: =+M45*L45 | L45: 19 | M45: 64.43 | N45: =+'TOTAL OPERACION'!R46 | O45: =N45*0.1 | P45: =N45+O45 | Q45: =N45+G45 | R45: =P45+I45
B46: =+B45+1 | C46: 2 | D46: 1 | E46: C | F46: =+'SITUACION COMERCIAL'!AB49 | G46: 290 | H46: =+G46*0.1 | I46: =+H46+G46 | J46: 319 | N46: =+'TOTAL OPERACION'!R47 | O46: =N46*0.1 | P46: =N46+O46 | Q46: =N46+G46 | R46: =P46+I46
B47: =+B46+1 | C47: 2 | D47: 1 | E47: D | F47: =+'SITUACION COMERCIAL'!AB50 | G47: 1615 | H47: =+G47*0.1 | I47: =+H47+G47 | J47: =+I47*0.4 | K47: =+I47-J47 | L47: 19 | M47: =+K47/L47 | N47: =+'TOTAL OPERACION'!R48 | O47: =N47*0.1 | P47: =N47+O47 | Q47: =N47+G47 | R47: =P47+I47
B48: =+B47+1 | C48: 2 | D48: 1 | E48: E | F48: =+'SITUACION COMERCIAL'!AB51 | H48: =+G48*0.1 | I48: =+H48+G48 | L48: 20 | N48: =+'TOTAL OPERACION'!R49 | O48: =N48*0.1 | P48: =N48+O48 | Q48: =N48+G48 | R48: =P48+I48
B49: =+B48+1 | C49: 2 | D49: 2 | E49: A | F49: =+'SITUACION COMERCIAL'!AB52 | G49: 2905 | H49: =+G49*0.1 | I49: =+H49+G49 | J49: 1278.4 | K49: =+L49*M49 | L49: 19 | M49: 100.9 | N49: =+'TOTAL OPERACION'!R50 | O49: =N49*0.1 | P49: =N49+O49 | Q49: =N49+G49 | R49: =P49+I49
B50: =+B49+1 | C50: 2 | D50: 2 | E50: B | F50: =+'SITUACION COMERCIAL'!AB53 | G50: 535 | H50: =+G50*0.1 | I50: =+H50+G50 | J50: =+I50 | L50: 20 | N50: =+'TOTAL OPERACION'!R51 | O50: =N50*0.1 | P50: =N50+O50 | Q50: =N50+G50 | R50: =P50+I50
B51: =+B50+1 | C51: 2 | D51: 2 | E51: C | F51: =+'SITUACION COMERCIAL'!AB54 | H51: =+G51*0.1 | I51: =+H51+G51 | L51: 20 | N51: =+'TOTAL OPERACION'!R52 | O51: =N51*0.1 | P51: =N51+O51 | Q51: =N51+G51 | R51: =P51+I51
B52: =+B51+1 | C52: 2 | D52: 2 | E52: D | F52: =+'SITUACION COMERCIAL'!AB55 | G52: 0 | H52: =+G52*0.1 | I52: =+H52+G52 | L52: 20 | N52: =+'TOTAL OPERACION'!R53 | O52: =N52*0.1 | P52: =N52+O52 | Q52: =N52+G52 | R52: =P52+I52
B53: =+B52+1 | C53: 2 | D53: 2 | E53: E | F53: =+'SITUACION COMERCIAL'!AB56 | H53: =+G53*0.1 | I53: =+H53+G53 | L53: 20 | N53: =+'TOTAL OPERACION'!R54 | O53: =N53*0.1 | P53: =N53+O53 | Q53: =N53+G53 | R53: =P53+I53
B54: =+B53+1 | C54: 2 | D54: 3 | E54: A | F54: =+'SITUACION COMERCIAL'!AB57 | G54: 1555 | H54: =+G54*0.1 | I54: =+H54+G54 | J54: 684.5 | K54: 1026 | L54: 19 | M54: =+K54/L54 | N54: =+'TOTAL OPERACION'!R55 | O54: =N54*0.1 | P54: =N54+O54 | Q54: =N54+G54 | R54: =P54+I54
B55: =+B54+1 | C55: 2 | D55: 3 | E55: B | F55: =+'SITUACION COMERCIAL'!AB58 | G55: 2150 | H55: =+G55*0.1 | I55: =+H55+G55 | J55: 946.08 | K55: =+L55*M55 | L55: 19 | M55: 74.68 | N55: =+'TOTAL OPERACION'!R56 | O55: =N55*0.1 | P55: =N55+O55 | Q55: =N55+G55 | R55: =P55+I55
B56: =+B55+1 | C56: 2 | D56: 3 | E56: C | F56: =+'SITUACION COMERCIAL'!AB59 | G56: 2335 | H56: =+G56*0.1 | I56: =+H56+G56 | J56: 1104.55 | K56: =+I56-J56 | L56: 19 | M56: =+K56/L56 | N56: =+'TOTAL OPERACION'!R57 | O56: =N56*0.1 | P56: =N56+O56 | Q56: =N56+G56 | R56: =P56+I56
B57: =+B56+1 | C57: 2 | D57: 3 | E57: D | F57: =+'SITUACION COMERCIAL'!AB60 | H57: =+G57*0.1 | I57: =+H57+G57 | L57: 20 | N57: =+'TOTAL OPERACION'!R58 | O57: =N57*0.1 | P57: =N57+O57 | Q57: =N57+G57 | R57: =P57+I57
B58: =+B57+1 | C58: 2 | D58: 3 | E58: E | F58: =+'SITUACION COMERCIAL'!AB61 | G58: 1785 | H58: =+G58*0.1 | I58: =+H58+G58 | J58: 785.5 | L58: 19 | M58: 62 | N58: =+'TOTAL OPERACION'!R59 | O58: =N58*0.1 | P58: =N58+O58 | Q58: =N58+G58 | R58: =P58+I58
B59: =+B58+1 | C59: 3 | D59: BAJA | E59: A | F59: =+'SITUACION COMERCIAL'!AB62 | G59: 560 | H59: =+G59*0.1 | I59: =+H59+G59 | J59: =+I59 | L59: 0 | N59: =+'TOTAL OPERACION'!R60 | O59: =N59*0.1 | P59: =N59+O59 | Q59: =N59+G59 | R59: =P59+I59
B60: =+B59+1 | C60: 3 | D60: BAJA | E60: B | F60: =+'SITUACION COMERCIAL'!AB63 | H60: =+G60*0.1 | I60: =+H60+G60 | L60: 20 | N60: =+'TOTAL OPERACION'!R61 | O60: =N60*0.1 | P60: =N60+O60 | Q60: =N60+G60 | R60: =P60+I60
B61: =+B60+1 | C61: 3 | D61: BAJA | E61: C | F61: =+'SITUACION COMERCIAL'!AB64 | G61: 5475 | H61: =+G61*0.1 | I61: =+H61+G61 | J61: 2503.7 | K61: =+L61*M61 | L61: 19 | M61: 185.2 | N61: =+'TOTAL OPERACION'!R62 | O61: =N61*0.1 | P61: =N61+O61 | Q61: =N61+G61 | R61: =P61+I61
B62: =+B61+1 | C62: 3 | D62: BAJA | E62: D | F62: =+'SITUACION COMERCIAL'!AB65 | G62: 3460 | H62: =+G62*0.1 | I62: =+H62+G62 | J62: 1552.52 | L62: 18 | M62: =+(I62-J62)/L62 | N62: =+'TOTAL OPERACION'!R63 | O62: =N62*0.1 | P62: =N62+O62 | Q62: =N62+G62 | R62: =P62+I62
B63: =+B62+1 | C63: 3 | D63: 1 | E63: A | F63: =+'SITUACION COMERCIAL'!AB66 | G63: 495 | H63: =+G63*0.1 | I63: =+H63+G63 | J63: =+I63-K63 | K63: 326.8 | L63: 19 | M63: =+K63/L63 | N63: =+'TOTAL OPERACION'!R64 | O63: =N63*0.1 | P63: =N63+O63 | Q63: =N63+G63 | R63: =P63+I63
B64: =+B63+1 | C64: 3 | D64: 1 | E64: B | F64: =+'SITUACION COMERCIAL'!AB67 | G64: 95 | H64: =+G64*0.1 | I64: =+H64+G64 | J64: =+I64 | L64: 20 | N64: =+'TOTAL OPERACION'!R65 | O64: =N64*0.1 | P64: =N64+O64 | Q64: =N64+G64 | R64: =P64+I64
B65: =+B64+1 | C65: 3 | D65: 1 | E65: C | F65: =+'SITUACION COMERCIAL'!AB68 | H65: =+G65*0.1 | I65: =+H65+G65 | L65: 20 | N65: =+'TOTAL OPERACION'!R66 | O65: =N65*0.1 | P65: =N65+O65 | Q65: =N65+G65 | R65: =P65+I65
B66: =+B65+1 | C66: 3 | D66: 1 | E66: D | F66: =+'SITUACION COMERCIAL'!AB69 | H66: =+G66*0.1 | I66: =+H66+G66 | L66: 20 | N66: =+'TOTAL OPERACION'!R67 | O66: =N66*0.1 | P66: =N66+O66 | Q66: =N66+G66 | R66: =P66+I66
B67: =+B66+1 | C67: 3 | D67: 2 | E67: A | F67: =+'SITUACION COMERCIAL'!AB70 | H67: =+G67*0.1 | I67: =+H67+G67 | L67: 20 | N67: =+'TOTAL OPERACION'!R68 | O67: =N67*0.1 | P67: =N67+O67 | Q67: =N67+G67 | R67: =P67+I67
B68: =+B67+1 | C68: 3 | D68: 2 | E68: B | F68: =+'SITUACION COMERCIAL'!AB71 | G68: 2820 | H68: =+G68*0.1 | I68: =+H68+G68 | J68: =+I68*0.4+0.15 | K68: =97.95*19 | L68: 19 | M68: =+K68/L68 | N68: =+'TOTAL OPERACION'!R69 | O68: =N68*0.1 | P68: =N68+O68 | Q68: =N68+G68 | R68: =P68+I68
B69: =+B68+1 | C69: 3 | D69: 2 | E69: C | F69: =+'SITUACION COMERCIAL'!AB72 | H69: =+G69*0.1 | I69: =+H69+G69 | L69: 20 | N69: =+'TOTAL OPERACION'!R70 | O69: =N69*0.1 | P69: =N69+O69 | Q69: =N69+G69 | R69: =P69+I69
B70: =+B69+1 | C70: 3 | D70: 2 | E70: D | F70: =+'SITUACION COMERCIAL'!AB73 | H70: =+G70*0.1 | I70: =+H70+G70 | L70: 20 | N70: =+'TOTAL OPERACION'!R71 | O70: =N70*0.1 | P70: =N70+O70 | Q70: =N70+G70 | R70: =P70+I70
B71: =+B70+1 | C71: 3 | D71: 3 | E71: A | F71: =+'SITUACION COMERCIAL'!AB74 | G71: 2420 | H71: =+G71*0.1 | I71: =+H71+G71 | J71: =+I71*0.4+0.06 | K71: =84.06*19 | L71: 19 | M71: =+K71/L71 | N71: =+'TOTAL OPERACION'!R72 | O71: =N71*0.1 | P71: =N71+O71 | Q71: =N71+G71 | R71: =P71+I71
B72: =+B71+1 | C72: 3 | D72: 3 | E72: B | F72: =+'SITUACION COMERCIAL'!AB75 | G72: 2520 | H72: =+G72*0.1 | I72: =+H72+G72 | J72: 1025.33 | L72: 19 | M72: 91.93 | N72: =+'TOTAL OPERACION'!R73 | O72: =N72*0.1 | P72: =N72+O72 | Q72: =N72+G72 | R72: =P72+I72
B73: =+B72+1 | C73: 3 | D73: 3 | E73: C | F73: =+'SITUACION COMERCIAL'!AB76 | G73: 685 | H73: =+G73*0.1 | I73: =+H73+G73 | J73: 753.5 | L73: 0 | N73: =+'TOTAL OPERACION'!R74 | O73: =N73*0.1 | P73: =N73+O73 | Q73: =N73+G73 | R73: =P73+I73
B74: =+B73+1 | C74: 3 | D74: 3 | E74: D | F74: =+'SITUACION COMERCIAL'!AB77 | H74: =+G74*0.1 | I74: =+H74+G74 | L74: 20 | N74: =+'TOTAL OPERACION'!R75 | P74: =N74+O74 | Q74: =N74+G74 | R74: =P74+I74
Q75: =SUM(Q9:Q74) | R75: =SUM(R9:R74)

Sheet TOTAL OPERACION
C1: IMPORTES TOTALES OPERACIÓN
C6: TITULAR 1 | G6: INMUEBLES | P6: PRECIOS
G7: Nº Orden | H7: VIVIENDA | L7: ANEXOS | P7: VIVIENDA | Q7: MEJORAS | R7: PORCELANICO | S7: TOTAL
H8: PORTAL | I8: PLANTA | J8: LETRA | K8: Nº Dorm. | L8: Garaje | M8: Trastero | N8: G. Adicional | O8: Tr. Adicional
C10: =+'SITUACION COMERCIAL'!AB12 | G10: 1 | H10: 1 | I10: BAJA | J10: A | K10: 4 | L10: 62 | M10: 56 | N10: . | O10: . | P10: =+'SITUACION COMERCIAL'!S12 | Q10: =+MEJORAS!G9 | R10: 4300 | S10: =+P10+Q10+R10
C11: =+'SITUACION COMERCIAL'!AB13 | G11: =+G10+1 | H11: 1 | I11: BAJA | J11: B | K11: 3 | L11: 57 | M11: 50 | N11: . | O11: . | P11: =+'SITUACION COMERCIAL'!S13 | Q11: =+MEJORAS!G10 | S11: =+P11+Q11+R11
C12: =+'SITUACION COMERCIAL'!AB14 | G12: 3 | H12: 1 | I12: BAJA | J12: C | K12: 2 | L12: NO | M12: 49 | N12: . | P12: =+'SITUACION COMERCIAL'!S14 | Q12: =+MEJORAS!G11 | S12: =+P12+Q12+R12
C13: =+'SITUACION COMERCIAL'!AB15 | G13: =+G12+1 | H13: 1 | I13: BAJA | J13: D | K13: 2 | L13: 40 | M13: 60 | N13: . | O13: . | P13: =+'SITUACION COMERCIAL'!S15 | Q13: =+MEJORAS!G12 | S13: =+P13+Q13+R13
C14: =+'SITUACION COMERCIAL'!AB28 | G14: =+G13+1 | H14: 1 | I14: BAJA | J14: E | K14: 2 | L14: 43 | M14: 18 | N14: . | O14: . | P14: =+'SITUACION COMERCIAL'!S16 | Q14: =+MEJORAS!G13 | S14: =+P14+Q14+R14
C15: =+'SITUACION COMERCIAL'!AB17 | G15: =+G14+1 | H15: 1 | I15: 1 | J15: A | K15: 4 | L15: 9 | M15: 13 | N15: - | O15: . | P15: =+'SITUACION COMERCIAL'!S17 | Q15: =+MEJORAS!G14 | R15: 4300 | S15: =+P15+Q15+R15
C16: =+'SITUACION COMERCIAL'!AB18 | G16: =+G15+1 | H16: 1 | I16: 1 | J16: B | K16: 3 | L16: 12 | M16: 16 | N16: . | O16: . | P16: =+'SITUACION COMERCIAL'!S18 | Q16: =+MEJORAS!G15 | S16: =+P16+Q16+R16
C17: =+'SITUACION COMERCIAL'!AB19 | G17: =+G16+1 | H17: 1 | I17: 1 | J17: C | K17: 2 | L17: 54 | M17: 48 | N17: . | O17: . | P17: =+'SITUACION COMERCIAL'!S19 | Q17: =+MEJORAS!G16 | R17: 2850 | S17: =+P17+Q17+R17
C18: =+'SITUACION COMERCIAL'!AB20 | G18: =+G17+1 | H18: 1 | I18: 1 | J18: D | K18: 2 | L18: 10 | M18: 14 | N18: . | O18: . | P18: =+'SITUACION COMERCIAL'!S20 | Q18: =+MEJORAS!G17 | S18: =+P18+Q18+R18
C19: =+'SITUACION COMERCIAL'!AB21 | G19: =+G18+1 | H19: 1 | I19: 1 | J19: E | K19: 2 | L19: 48 | M19: . | N19: . | O19: . | P19: =+'SITUACION COMERCIAL'!S21 | Q19: =+MEJORAS!G18 | S19: =+P19+Q19+R19
C20: =+'SITUACION COMERCIAL'!AB22 | G20: =+G19+1 | H20: 1 | I20: 1 | J20: F | K20: 2 | L20: 14 | M20: 21 | N20: . | O20: . | P20: =+'SITUACION COMERCIAL'!S22 | Q20: =+MEJORAS!G19 | S20: =+P20+Q20+R20
C21: =+'SITUACION COMERCIAL'!AB23 | G21: =+G20+1 | H21: 1 | I21: 2 | J21: A | K21: 4 | L21: 60 | M21: 54 | N21: . | O21: . | P21: =+'SITUACION COMERCIAL'!S23 | Q21: =+MEJORAS!G20 | R21: 4300 | S21: =+P21+Q21+R21
C22: =+'SITUACION COMERCIAL'!AB24 | G22: =+G21+1 | H22: 1 | I22: 2 | J22: B | K22: 3 | L22: 13 | M22: 20 | N22: . | O22: . | P22: =+'SITUACION COMERCIAL'!S24 | Q22: =+MEJORAS!G21 | R22: 3990 | S22: =+P22+Q22+R22
C23: =+'SITUACION COMERCIAL'!AB25 | G23: =+G22+1 | H23: 1 | I23: 2 | J23: C | K23: 2 | L23: 44 | M23: 43 | N23: . | O23: . | P23: =+'SITUACION COMERCIAL'!S25 | Q23: =+MEJORAS!G22 | R23: 2850 | S23: =+P23+Q23+R23
C24: =+'SITUACION COMERCIAL'!AB26 | G24: =+G23+1 | H24: 1 | I24: 2 | J24: D | K24: 2 | L24: 15 | M24: 22 | N24: . | O24: . | P24: =+'SITUACION COMERCIAL'!S26 | Q24: =+MEJORAS!G23 | S24: =+P24+Q24+R24
C25: =+'SITUACION COMERCIAL'!AB27 | G25: =+G24+1 | H25: 1 | I25: 2 | J25: E | K25: 2 | L25: 58 | M25: 51 | P25: =+'SITUACION COMERCIAL'!S27 | Q25: =+MEJORAS!G24 | S25: =+P25+Q25+R25
C26: =+'SITUACION COMERCIAL'!#REF! | G26: =+G25+1 | H26: 1 | I26: 2 | J26: F | K26: 2 | L26: 42 | M26: 42 | N26: . | O26: . | P26: =+'SITUACION COMERCIAL'!S28 | Q26: =+MEJORAS!G25 | S26: =+P26+Q26+R26
C27: =+'SITUACION COMERCIAL'!AB29 | G27: =+G26+1 | H27: 1 | I27: 3 | J27: A | K27: 4 | L27: 59 | M27: 53 | N27: 50 | O27: . | P27: =+'SITUACION COMERCIAL'!S29 | Q27: =+MEJORAS!G26 | S27: =+P27+Q27+R27
C28: =+'SITUACION COMERCIAL'!AB30 | G28: =+G27+1 | H28: 1 | I28: 3 | J28: B | K28: 3 | L28: 16 | M28: 23 | N28: . | O28: . | P28: =+'SITUACION COMERCIAL'!S30 | Q28: =+MEJORAS!G27 | S28: =+P28+Q28+R28
C29: =+'SITUACION COMERCIAL'!AB31 | G29: =+G28+1 | H29: 1 | I29: 3 | J29: C | K29: 2 | L29: 38 | M29: 25 | N29: . | O29: . | P29: =+'SITUACION COMERCIAL'!S31 | Q29: =+MEJORAS!G28 | S29: =+P29+Q29+R29
C30: =+'SITUACION COMERCIAL'!AB32 | G30: =+G29+1 | H30: 1 | I30: 3 | J30: D | K30: 2 | L30: 45 | M30: 44 | N30: . | O30: . | P30: =+'SITUACION COMERCIAL'!S32 | Q30: =+MEJORAS!G29 | S30: =+P30+Q30+R30
C31: =+'SITUACION COMERCIAL'!AB33 | G31: =+G30+1 | H31: 1 | I31: 3 | J31: E | K31: 2 | L31: 11 | M31: 15 | N31: . | O31: . | P31: =+'SITUACION COMERCIAL'!S33 | Q31: =+MEJORAS!G30 | S31: =+P31+Q31+R31
C32: =+'SITUACION COMERCIAL'!AB34 | G32: =+G31+1 | H32: 1 | I32: 3 | J32: F | K32: 2 | L32: 51 | M32: 46 | N32: . | O32: . | P32: =+'SITUACION COMERCIAL'!S34 | Q32: =+MEJORAS!G31 | S32: =+P32+Q32+R32
C33: =+'SITUACION COMERCIAL'!AB35 | G33: =+G32+1 | H33: 1 | I33: 4 | J33: A | K33: 4 | L33: 41 | M33: 52 | N33: . | O33: . | P33: =+'SITUACION COMERCIAL'!S35 | Q33: =+MEJORAS!G32 | S33: =+P33+Q33+R33
C34: =+'SITUACION COMERCIAL'!AB36 | G34: =+G33+1 | H34: 1 | I34: 4 | J34: B | K34: 2 | L34: 8 | M34: 12 | N34: . | O34: . | P34: =+'SITUACION COMERCIAL'!S36 | Q34: =+MEJORAS!G33 | S34: =+P34+Q34+R34
C35: =+'SITUACION COMERCIAL'!AB37 | G35: =+G34+1 | H35: 1 | I35: 4 | J35: C | K35: 2 | L35: 65 | M35: 59 | N35: . | O35: . | P35: =+'SITUACION COMERCIAL'!S37 | Q35: =+MEJORAS!G34 | S35: =+P35+Q35+R35
C36: =+'SITUACION COMERCIAL'!AB38 | G36: =+G35+1 | H36: 1 | I36: 4 | J36: D | K36: 2 | L36: 53 | M36: 19 | N36: . | O36: . | P36: =+'SITUACION COMERCIAL'!S38 | Q36: =+MEJORAS!G35 | S36: =+P36+Q36+R36
C37: =+'SITUACION COMERCIAL'!AB39 | G37: =+G36+1 | H37: 1 | I37: 5 | J37: A | K37: 4 | L37: 52 | M37: 47 | N37: 49 | O37: . | P37: 267700 | Q37: =+MEJORAS!G36 | S37: =+P37+Q37+R37
C38: =+'SITUACION COMERCIAL'!AB40 | G38: =+G37+1 | H38: 1 | I38: 5 | J38: B | K38: 4 | L38: 6 | M38: 10 | N38: . | O38: . | P38: =+'SITUACION COMERCIAL'!S40 | Q38: =+MEJORAS!G37 | S38: =+P38+Q38+R38
C39: =+'SITUACION COMERCIAL'!AB41 | G39: =+G38+1 | H39: 1 | I39: 5 | J39: C | K39: 4 | L39: 46 | M39: 45 | N39: . | O39: . | P39: =+'SITUACION COMERCIAL'!S41 | Q39: =+MEJORAS!G38 | S39: =+P39+Q39+R39
C40: =+'SITUACION COMERCIAL'!AB42 | G40: =+G39+1 | H40: 2 | I40: BAJA | J40: A | K40: 5 | L40: 22 | M40: 30 | N40: . | O40: . | P40: =+'SITUACION COMERCIAL'!S42 | Q40: =+MEJORAS!G39 | S40: =+P40+Q40+R40
C41: =+'SITUACION COMERCIAL'!AB43 | G41: =+G40+1 | H41: 2 | I41: BAJA | J41: B | K41: 4 | L41: 21 | M41: 29 | N41: . | O41: . | P41: =+'SITUACION COMERCIAL'!S43 | Q41: =+MEJORAS!G40 | S41: =+P41+Q41+R41
C42: =+'SITUACION COMERCIAL'!AB44 | G42: =+G41+1 | H42: 2 | I42: BAJA | J42: C | K42: 3 | L42: 33 | M42: 5 | N42: . | O42: . | P42: =+'SITUACION COMERCIAL'!S44 | Q42: =+MEJORAS!G41 | S42: =+P42+Q42+R42
C43: =+'SITUACION COMERCIAL'!AB45 | G43: =+G42+1 | H43: 2 | I43: BAJA | J43: D | K43: 2 | L43: 20 | M43: 28 | N43: . | O43: . | P43: =+'SITUACION COMERCIAL'!S45 | Q43: =+MEJORAS!G42 | S43: =+P43+Q43+R43
C44: =+'SITUACION COMERCIAL'!AB46 | G44: =+G43+1 | H44: 2 | I44: BAJA | J44: E | K44: 3 | L44: 19 | M44: 27 | N44: . | O44: . | P44: =+'SITUACION COMERCIAL'!S46 | Q44: =+MEJORAS!G43 | S44: =+P44+Q44+R44
C45: =+'SITUACION COMERCIAL'!AB47 | G45: =+G44+1 | H45: 2 | I45: 1 | J45: A | K45: 5 | L45: 61 | M45: 55 | N45: 39 | O45: . | P45: =+'SITUACION COMERCIAL'!S47 | Q45: =+MEJORAS!G44 | R45: 5750 | S45: =+P45+Q45+R45
C46: =+'SITUACION COMERCIAL'!AB48 | G46: =+G45+1 | H46: 2 | I46: 1 | J46: B | K46: 4 | L46: 34 | M46: 17 | N46: . | O46: . | P46: =+'SITUACION COMERCIAL'!S48 | Q46: =+MEJORAS!G45 | S46: =+P46+Q46+R46
C47: =+'SITUACION COMERCIAL'!AB49 | G47: =+G46+1 | H47: 2 | I47: 1 | J47: C | K47: 3 | L47: 3 | M47: 3 | N47: . | O47: . | P47: =+'SITUACION COMERCIAL'!S49 | Q47: =+MEJORAS!G46 | S47: =+P47+Q47+R47
C48: =+'SITUACION COMERCIAL'!AB50 | G48: =+G47+1 | H48: 2 | I48: 1 | J48: D | K48: 2 | L48: 36 | M48: 39 | N48: . | O48: . | P48: =+'SITUACION COMERCIAL'!S50 | Q48: =+MEJORAS!G47 | R48: 2850 | S48: =+P48+Q48+R48
C49: =+'SITUACION COMERCIAL'!AB51 | G49: =+G48+1 | H49: 2 | I49: 1 | J49: E | K49: 3 | L49: 4 | M49: 4 | N49: . | O49: . | P49: =+'SITUACION COMERCIAL'!S51 | Q49: =+MEJORAS!G48 | R49: 3990 | S49: =+P49+Q49+R49
C50: =+'SITUACION COMERCIAL'!AB52 | G50: =+G49+1 | H50: 2 | I50: 2 | J50: A | K50: 5 | L50: 64 | M50: 58 | N50: 35 | O50: . | P50: =+'SITUACION COMERCIAL'!S52 | Q50: =+MEJORAS!G49 | S50: =+P50+Q50+R50
C51: =+'SITUACION COMERCIAL'!AB53 | G51: =+G50+1 | H51: 2 | I51: 2 | J51: B | K51: 4 | L51: 17 | M51: 24 | N51: . | O51: . | P51: =+'SITUACION COMERCIAL'!S53 | Q51: =+MEJORAS!G50 | S51: =+P51+Q51+R51
C52: =+'SITUACION COMERCIAL'!AB54 | G52: =+G51+1 | H52: 2 | I52: 2 | J52: C | K52: 3 | L52: 7 | M52: 11 | N52: . | O52: . | P52: =+'SITUACION COMERCIAL'!S54 | Q52: =+MEJORAS!G51 | S52: =+P52+Q52+R52
C53: =+'SITUACION COMERCIAL'!AB55 | G53: =+G52+1 | H53: 2 | I53: 2 | J53: D | K53: 2 | L53: 66 | M53: 61 | N53: . | O53: . | P53: =+'SITUACION COMERCIAL'!S55 | Q53: =+MEJORAS!G52 | S53: =+P53+Q53+R53
C54: =+'SITUACION COMERCIAL'!AB56 | G54: =+G53+1 | H54: 2 | I54: 2 | J54: E | K54: 3 | L54: 5 | M54: 8 | N54: . | O54: . | P54: =+'SITUACION COMERCIAL'!S56 | Q54: =+MEJORAS!G53 | S54: =+P54+Q54+R54
C55: =+'SITUACION COMERCIAL'!AB57 | G55: =+G54+1 | H55: 2 | I55: 3 | J55: A | K55: 5 | L55: 63 | M55: 57 | N55: . | O55: . | P55: =+'SITUACION COMERCIAL'!S57 | Q55: =+MEJORAS!G54 | R55: 5750 | S55: =+P55+Q55+R55
C56: =+'SITUACION COMERCIAL'!AB58 | G56: =+G55+1 | H56: 2 | I56: 3 | J56: B | K56: 4 | L56: 37 | M56: 40 | N56: . | O56: . | P56: =+'SITUACION COMERCIAL'!S58 | Q56: =+MEJORAS!G55 | S56: =+P56+Q56+R56
C57: =+'SITUACION COMERCIAL'!AB59 | G57: =+G56+1 | H57: 2 | I57: 3 | J57: C | K57: 3 | L57: 18 | M57: 26 | N57: . | O57: . | P57: =+'SITUACION COMERCIAL'!S59 | Q57: =+MEJORAS!G56 | S57: =+P57+Q57+R57
C58: =+'SITUACION COMERCIAL'!AB60 | G58: =+G57+1 | H58: 2 | I58: 3 | J58: D | K58: 2 | L58: 67 | M58: 62 | N58: . | O58: . | P58: =+'SITUACION COMERCIAL'!S60 | Q58: =+MEJORAS!G57 | S58: =+P58+Q58+R58
C59: =+'SITUACION COMERCIAL'!AB61 | G59: =+G58+1 | H59: 2 | I59: 3 | J59: E | K59: 3 | L59: 23 | M59: 31 | N59: . | O59: . | P59: =+'SITUACION COMERCIAL'!S61 | Q59: =+MEJORAS!G58 | S59: =+P59+Q59+R59
C60: =+'SITUACION COMERCIAL'!AB62 | G60: =+G59+1 | H60: 3 | I60: BAJA | J60: A | K60: 3 | L60: 1 | M60: 1 | N60: . | O60: . | P60: =+'SITUACION COMERCIAL'!S62 | Q60: =+MEJORAS!G59 | S60: =+P60+Q60+R60
C61: =+'SITUACION COMERCIAL'!AB63 | G61: =+G60+1 | H61: 3 | I61: BAJA | J61: B | K61: 4 | L61: 2 | M61: 2 | N61: . | O61: . | P61: =+'SITUACION COMERCIAL'!S63 | Q61: =+MEJORAS!G60 | S61: =+P61+Q61+R61
C62: =+'SITUACION COMERCIAL'!AB64 | G62: =+G61+1 | H62: 3 | I62: BAJA | J62: C | K62: 4 | L62: 27 | M62: 36 | N62: 55 | O62: . | P62: =+'SITUACION COMERCIAL'!S64 | Q62: =+MEJORAS!G61 | S62: =+P62+Q62+R62
C63: =+'SITUACION COMERCIAL'!AB65 | G63: =+G62+1 | H63: 3 | I63: BAJA | J63: D | K63: 3 | L63: 26 | M63: 35 | N63: . | O63: . | P63: =+'SITUACION COMERCIAL'!S65 | Q63: =+MEJORAS!G62 | S63: =+P63+Q63+R63
C64: =+'SITUACION COMERCIAL'!AB66 | G64: =+G63+1 | H64: 3 | I64: 1 | J64: A | K64: 3 | L64: 28 | M64: 37 | N64: . | O64: . | P64: =+'SITUACION COMERCIAL'!S66 | Q64: =+MEJORAS!G63 | S64: =+P64+Q64+R64
C65: =+'SITUACION COMERCIAL'!AB67 | G65: =+G64+1 | H65: 3 | I65: 1 | J65: B | K65: 4 | L65: 29 | M65: 38 | N65: . | O65: . | P65: =+'SITUACION COMERCIAL'!S67 | Q65: =+MEJORAS!G64 | S65: =+P65+Q65+R65
C66: =+'SITUACION COMERCIAL'!AB68 | G66: =+G65+1 | H66: 3 | I66: 1 | J66: C | K66: 4 | L66: 30 | M66: 34 | N66: . | O66: . | P66: =+'SITUACION COMERCIAL'!S68 | Q66: =+MEJORAS!G65 | R66: 4300 | S66: =+P66+Q66+R66
C67: =+'SITUACION COMERCIAL'!AB69 | G67: =+G66+1 | H67: 3 | I67: 1 | J67: D | K67: 3 | L67: 32 | M67: 41 | N67: . | O67: . | P67: =+'SITUACION COMERCIAL'!S69 | Q67: =+MEJORAS!G66 | S67: =+P67+Q67+R67
C68: =+'SITUACION COMERCIAL'!AB70 | G68: =+G67+1 | H68: 3 | I68: 2 | J68: A | K68: 3 | L68: 72 | M68: 67 | N68: . | O68: . | P68: =+'SITUACION COMERCIAL'!S70 | Q68: =+MEJORAS!G67 | S68: =+P68+Q68+R68
C69: =+'SITUACION COMERCIAL'!AB71 | G69: =+G68+1 | H69: 3 | I69: 2 | J69: B | K69: 4 | L69: 25 | M69: 33 | N69: . | O69: . | P69: =+'SITUACION COMERCIAL'!S71 | Q69: =+MEJORAS!G68 | R69: 4300 | S69: =+P69+Q69+R69
C70: =+'SITUACION COMERCIAL'!AB72 | G70: =+G69+1 | H70: 3 | I70: 2 | J70: C | K70: 4 | L70: 24 | M70: 32 | N70: . | O70: . | P70: =+'SITUACION COMERCIAL'!S72 | Q70: =+MEJORAS!G69 | S70: =+P70+Q70+R70
C71: =+'SITUACION COMERCIAL'!AB73 | G71: =+G70+1 | H71: 3 | I71: 2 | J71: D | K71: 3 | L71: 31 | M71: 6 | N71: . | O71: . | P71: =+'SITUACION COMERCIAL'!S73 | Q71: =+MEJORAS!G70 | S71: =+P71+Q71+R71
C72: =+'SITUACION COMERCIAL'!AB74 | G72: =+G71+1 | H72: 3 | I72: 3 | J72: A | K72: 3 | L72: 71 | M72: 66 | N72: 56 | O72: . | P72: =+'SITUACION COMERCIAL'!S74 | Q72: =+MEJORAS!G71 | S72: =+P72+Q72+R72
C73: =+'SITUACION COMERCIAL'!AB75 | G73: =+G72+1 | H73: 3 | I73: 3 | J73: B | K73: 4 | L73: 70 | M73: 65 | N73: . | O73: . | P73: =+'SITUACION COMERCIAL'!S75 | Q73: =+MEJORAS!G72 | R73: 4300 | S73: =+P73+Q73+R73
C74: =+'SITUACION COMERCIAL'!AB76 | G74: =+G73+1 | H74: 3 | I74: 3 | J74: C | K74: 4 | L74: 69 | M74: 64 | N74: . | O74: . | P74: =+'SITUACION COMERCIAL'!S76 | Q74: =+MEJORAS!G73 | S74: =+P74+Q74+R74
C75: =+'SITUACION COMERCIAL'!AB77 | G75: =+G74+1 | H75: 3 | I75: 3 | J75: D | K75: 3 | L75: 68 | M75: 63 | N75: . | O75: . | P75: =+'SITUACION COMERCIAL'!S77 | Q75: =+MEJORAS!G74 | S75: =+P75+Q75+R75
P76: =SUM(P10:P75) | Q76: =SUM(Q10:Q75) | R76: =SUM(R10:R75) | S76: =SUM(S10:S75)

Sheet FACTURACION
F1: =+F5+F13+F35+F36+F38+F56 | G1: =+F1*0.25
E3: TITULAR ACTUAL | F3: Precio base con actualizacion | G3: Origen | H3: Honorarios totales | K3: Liquidacion 1 | L3: liquidación 2 | M3: liq. 31/05/2024 | N3: liquidación agosto | O3: Liquidacion 2/09/24 | P3: lLiquidación 10/2024 | Q3: 45890 | R3: 45930 | S3: 46010 | U3: FACTURADO | V3: pte FACTURAR | W3: PTE A ENTREGA
H4: Importe | I4: % | J4: devengados | K4: 25% h. totales | L4: 50% h. totales-liquidación1 | M4: 50% honorarios totales | N4: 50% honorarios totales | O4: 50% honorarios totales | P4: 50% honorarios totales | Q4: 50% honorarios totales | R4: 50% honorarios totales | S4: 50% honorarios totales
A5: 1 | B5: 1 | C5: BAJA | D5: A | E5: =+'SITUACION COMERCIAL'!AB12 | F5: =IF('SITUACION COMERCIAL'!A12="RESERVADO",'SITUACION COMERCIAL'!S12,0) | G5: HABITAT | H5: =IF(G5="HABITAT",F5*0.025,F5*0.02) | I5: =+H5/F5 | J5: =IF('SITUACION COMERCIAL'!A12="RESERVADO",H5/2,0) | K5: 0 | L5: 3875 | Q5: -3875 | U5: =SUM(K5:T5) | V5: =+J5-K5-L5-M5-N5-O5-P5-T5-Q5-R5-S5 | W5: =+H5-U5 | X5: AARON ALEJANDRO VALVERDE VILLALON
A6: =+A5+1 | B6: 1 | C6: BAJA | D6: B | E6: =+'SITUACION COMERCIAL'!AB13 | F6: =IF('SITUACION COMERCIAL'!A13="RESERVADO",'SITUACION COMERCIAL'!S13,0) | G6: HABITAT | H6: =IF(G6="HABITAT",F6*0.025,F6*0.02) | I6: =+H6/F6 | J6: =IF('SITUACION COMERCIAL'!A13="RESERVADO",H6/2,0) | K6: 1468.125 | L6: 1468.125 | U6: =SUM(K6:T6) | V6: =+J6-K6-L6-M6-N6-O6-P6-T6-Q6-R6-S6 | W6: =+H6-U6 | X6: MANUEL PEÑA GRAGERA
A7: 3 | B7: 1 | C7: BAJA | D7: C | E7: =+'SITUACION COMERCIAL'!AB14 | F7: =IF('SITUACION COMERCIAL'!A14="RESERVADO",'SITUACION COMERCIAL'!S14,0) | G7: HABITAT | H7: =IF(G7="HABITAT",F7*0.025,F7*0.02) | I7: =+H7/F7 | J7: =IF('SITUACION COMERCIAL'!A14="RESERVADO",H7/2,0) | L7: 0 | O7: 1912.5 | U7: =SUM(K7:T7) | V7: =+J7-K7-L7-M7-N7-O7-P7-T7-Q7-R7-S7 | W7: =+H7-U7
A8: =+A7+1 | B8: 1 | C8: BAJA | D8: D | E8: =+'SITUACION COMERCIAL'!AB15 | F8: =IF('SITUACION COMERCIAL'!A15="RESERVADO",'SITUACION COMERCIAL'!S15,0) | G8: HABITAT | H8: =IF(G8="HABITAT",F8*0.025,F8*0.02) | I8: =+H8/F8 | J8: =IF('SITUACION COMERCIAL'!A15="RESERVADO",H8/2,0) | K8: 0 | L8: 2225 | U8: =SUM(K8:T8) | V8: =+J8-K8-L8-M8-N8-O8-P8-T8-Q8-R8-S8 | W8: =+H8-U8 | X8: ISIDORA ROMERO MARTIN
A9: =+A8+1 | B9: 1 | C9: BAJA | D9: E | E9: =+'SITUACION COMERCIAL'!AB16 | F9: =IF('SITUACION COMERCIAL'!A16="RESERVADO",'SITUACION COMERCIAL'!S16,0) | G9: HABITAT | H9: =IF(G9="HABITAT",F9*0.025,F9*0.02) | I9: =+H9/F9 | J9: =IF('SITUACION COMERCIAL'!A16="RESERVADO",H9/2,0) | Q9: 2687.5 | U9: =SUM(K9:T9) | V9: =+J9-K9-L9-M9-N9-O9-P9-T9-Q9-R9-S9 | W9: =+H9-U9
A10: =+A9+1 | B10: 1 | C10: 1 | D10: A | E10: =+'SITUACION COMERCIAL'!AB17 | F10: =IF('SITUACION COMERCIAL'!A17="RESERVADO",'SITUACION COMERCIAL'!S17,0) | G10: HABITAT | H10: =IF(G10="HABITAT",F10*0.025,F10*0.02) | I10: =+H10/F10 | J10: =IF('SITUACION COMERCIAL'!A17="RESERVADO",H10/2,0) | K10: 0 | L10: 3792.5 | U10: =SUM(K10:T10) | V10: =+J10-K10-L10-M10-N10-O10-P10-T10-Q10-R10-S10 | W10: =+H10-U10 | X10: JOSE MARIA PRUDENCIO ALONSO
A11: =+A10+1 | B11: 1 | C11: 1 | D11: B | E11: =+'SITUACION COMERCIAL'!AB18 | F11: =IF('SITUACION COMERCIAL'!A18="RESERVADO",'SITUACION COMERCIAL'!S18,0) | G11: HABITAT | H11: =IF(G11="HABITAT",F11*0.025,F11*0.02) | I11: =+H11/F11 | J11: =IF('SITUACION COMERCIAL'!A18="RESERVADO",H11/2,0) | R11: 3275 | U11: =SUM(K11:T11) | V11: =+J11-K11-L11-M11-N11-O11-P11-T11-Q11-R11-S11 | W11: =+H11-U11
A12: =+A11+1 | B12: 1 | C12: 1 | D12: C | E12: =+'SITUACION COMERCIAL'!AB19 | F12: =IF('SITUACION COMERCIAL'!A19="RESERVADO",'SITUACION COMERCIAL'!S19,0) | G12: HABITAT | H12: =IF(G12="HABITAT",F12*0.025,F12*0.02) | I12: =+H12/F12 | J12: =IF('SITUACION COMERCIAL'!A19="RESERVADO",H12/2,0) | K12: 1105 | L12: 1067.725 | U12: =SUM(K12:T12) | V12: =+J12-K12-L12-M12-N12-O12-P12-T12-Q12-R12-S12 | W12: =+H12-U12 | X12: AMALIA CABANILLAS BAENA
A13: =+A12+1 | B13: 1 | C13: 1 | D13: D | E13: =+'SITUACION COMERCIAL'!AB20 | F13: =IF('SITUACION COMERCIAL'!A20="RESERVADO",'SITUACION COMERCIAL'!S20,0) | G13: HABITAT | H13: =IF(G13="HABITAT",F13*0.025,F13*0.02) | I13: =+H13/F13 | J13: =IF('SITUACION COMERCIAL'!A20="RESERVADO",H13/2,0) | S13: 2612.5 | U13: =SUM(K13:T13)-K13 | V13: =+J13-K13-L13-M13-N13-O13-P13-T13-Q13-R13-S13 | W13: =+H13-U13
A14: =+A13+1 | B14: 1 | C14: 1 | D14: E | E14: =+'SITUACION COMERCIAL'!AB21 | F14: =IF('SITUACION COMERCIAL'!A21="RESERVADO",'SITUACION COMERCIAL'!S21,0) | G14: HABITAT | H14: =IF(G14="HABITAT",F14*0.025,F14*0.02) | I14: =+H14/F14 | J14: =IF('SITUACION COMERCIAL'!A21="RESERVADO",H14/2,0) | K14: 0 | L14: 2225 | U14: =SUM(K14:T14) | V14: =+J14-K14-L14-M14-N14-O14-P14-T14-Q14-R14-S14 | W14: =+H14-U14 | X14: VICTOR JOSE ROJAS MORENO
A15: =+A14+1 | B15: 1 | C15: 1 | D15: F | E15: =+'SITUACION COMERCIAL'!AB22 | F15: =IF('SITUACION COMERCIAL'!A22="RESERVADO",'SITUACION COMERCIAL'!S22,0) | G15: HABITAT | H15: =IF(G15="HABITAT",F15*0.025,F15*0.02) | I15: =+H15/F15 | J15: =IF('SITUACION COMERCIAL'!A22="RESERVADO",H15/2,0) | N15: 2312.5 | U15: =SUM(K15:T15) | V15: =+J15-K15-L15-M15-N15-O15-P15-T15-Q15-R15-S15 | W15: =+H15-U15 | X15: JUAN MANUEL DURAN GUERRERO
A16: =+A15+1 | B16: 1 | C16: 2 | D16: A | E16: =+'SITUACION COMERCIAL'!AB23 | F16: =IF('SITUACION COMERCIAL'!A23="RESERVADO",'SITUACION COMERCIAL'!S23,0) | G16: EDETICA | H16: =IF(G16="HABITAT",F16*0.025,F16*0.02) | I16: =+H16/F16 | J16: =IF('SITUACION COMERCIAL'!A23="RESERVADO",H16/2,0) | K16: 1399.5 | L16: 1399.5 | U16: =SUM(K16:T16) | V16: =+J16-K16-L16-M16-N16-O16-P16-T16-Q16-R16-S16 | W16: =+H16-U16 | X16: IGNACIO AMARO BLANCO
A17: =+A16+1 | B17: 1 | C17: 2 | D17: B | E17: =+'SITUACION COMERCIAL'!AB24 | F17: =IF('SITUACION COMERCIAL'!A24="RESERVADO",'SITUACION COMERCIAL'!S24,0) | G17: HABITAT | H17: =IF(G17="HABITAT",F17*0.025,F17*0.02) | I17: =+H17/F17 | J17: =IF('SITUACION COMERCIAL'!A24="RESERVADO",H17/2,0) | K17: 1491.25 | L17: 1491.25 | U17: =SUM(K17:T17) | V17: =+J17-K17-L17-M17-N17-O17-P17-T17-Q17-R17-S17 | W17: =+H17-U17 | X17: SATURNINO GONZALEZ -HABA GIL
A18: =+A17+1 | B18: 1 | C18: 2 | D18: C | E18: =+'SITUACION COMERCIAL'!AB25 | F18: =IF('SITUACION COMERCIAL'!A25="RESERVADO",'SITUACION COMERCIAL'!S25,0) | G18: HABITAT | H18: =IF(G18="HABITAT",F18*0.025,F18*0.02) | I18: =+H18/F18 | J18: =IF('SITUACION COMERCIAL'!A25="RESERVADO",H18/2,0) | K18: 1118.125 | L18: 1118.125 | U18: =SUM(K18:T18) | V18: =+J18-K18-L18-M18-N18-O18-P18-T18-Q18-R18-S18 | W18: =+H18-U18 | X18: JUAN FRANCISCO OTERO MARTIN
A19: =+A18+1 | B19: 1 | C19: 2 | D19: D | E19: =+'SITUACION COMERCIAL'!AB26 | F19: =IF('SITUACION COMERCIAL'!A26="RESERVADO",'SITUACION COMERCIAL'!S26,0) | G19: HABITAT | H19: =IF(G19="HABITAT",F19*0.025,F19*0.02) | I19: =+H19/F19 | J19: =IF('SITUACION COMERCIAL'!A26="RESERVADO",H19/2,0) | M19: 2312.5 | U19: =SUM(K19:T19)-K19 | V19: =+J19-K19-L19-M19-N19-O19-P19-T19-Q19-R19-S19 | W19: =+H19-U19 | X19: MARIA JESUS FERNANDEZ SANCHEZ
A20: =+A19+1 | B20: 1 | C20: 2 | D20: E | E20: =+'SITUACION COMERCIAL'!AB27 | F20: =IF('SITUACION COMERCIAL'!A27="RESERVADO",'SITUACION COMERCIAL'!S27,0) | G20: HABITAT | H20: =IF(G20="HABITAT",F20*0.025,F20*0.02) | I20: =+H20/F20 | J20: =IF('SITUACION COMERCIAL'!A27="RESERVADO",H20/2,0) | K20: 1087.5 | L20: 1175 | U20: =SUM(K20:T20) | V20: =+J20-K20-L20-M20-N20-O20-P20-T20-Q20-R20-S20 | W20: =+H20-U20 | X20: MANUEL JOSE SUAREZ MARTIN
A21: =+A20+1 | B21: 1 | C21: 2 | D21: F | E21: =+'SITUACION COMERCIAL'!AB28 | F21: =IF('SITUACION COMERCIAL'!A28="RESERVADO",'SITUACION COMERCIAL'!S28,0) | G21: HABITAT | H21: =IF(G21="HABITAT",F21*0.025,F21*0.02) | I21: =+H21/F21 | J21: =IF('SITUACION COMERCIAL'!A28="RESERVADO",H21/2,0) | N21: 2337.5 | U21: =SUM(K21:T21)-K21 | V21: =+J21-K21-L21-M21-N21-O21-P21-T21-Q21-R21-S21 | W21: =+H21-U21
A22: =+A21+1 | B22: 1 | C22: 3 | D22: A | E22: =+'SITUACION COMERCIAL'!AB29 | F22: =IF('SITUACION COMERCIAL'!A29="RESERVADO",'SITUACION COMERCIAL'!S29,0) | G22: HABITAT | H22: =IF(G22="HABITAT",F22*0.025,F22*0.02) | I22: =+H22/F22 | J22: =IF('SITUACION COMERCIAL'!A29="RESERVADO",H22/2,0) | K22: 1875.625 | L22: 1875.625 | U22: =SUM(K22:T22) | V22: =+J22-K22-L22-M22-N22-O22-P22-T22-Q22-R22-S22 | W22: =+H22-U22 | X22: DIEGO GARCIA RUBIO
A23: =+A22+1 | B23: 1 | C23: 3 | D23: B | E23: =+'SITUACION COMERCIAL'!AB30 | F23: =IF('SITUACION COMERCIAL'!A30="RESERVADO",'SITUACION COMERCIAL'!S30,0) | G23: HABITAT | H23: =IF(G23="HABITAT",F23*0.025,F23*0.02) | I23: =+H23/F23 | J23: =IF('SITUACION COMERCIAL'!A30="RESERVADO",H23/2,0) | K23: 1498.125 | L23: 1498.125 | U23: =SUM(K23:T23) | V23: =+J23-K23-L23-M23-N23-O23-P23-T23-Q23-R23-S23 | W23: =+H23-U23 | X23: FELIPA PEREZ CORRALES
A24: =+A23+1 | B24: 1 | C24: 3 | D24: C | E24: =+'SITUACION COMERCIAL'!AB31 | F24: =IF('SITUACION COMERCIAL'!A31="RESERVADO",'SITUACION COMERCIAL'!S31,0) | G24: HABITAT | H24: =IF(G24="HABITAT",F24*0.025,F24*0.02) | I24: =+H24/F24 | J24: =IF('SITUACION COMERCIAL'!A31="RESERVADO",H24/2,0) | K24: 1135 | L24: 1135 | U24: =SUM(K24:T24) | V24: =+J24-K24-L24-M24-N24-O24-P24-T24-Q24-R24-S24 | W24: =+H24-U24 | X24: PAULINO CONEJO NAVARRETE
A25: =+A24+1 | B25: 1 | C25: 3 | D25: D | E25: =+'SITUACION COMERCIAL'!AB32 | F25: =IF('SITUACION COMERCIAL'!A32="RESERVADO",'SITUACION COMERCIAL'!S32,0) | G25: HABITAT | H25: =IF(G25="HABITAT",F25*0.025,F25*0.02) | I25: =+H25/F25 | J25: =IF('SITUACION COMERCIAL'!A32="RESERVADO",H25/2,0) | K25: 1150 | L25: 1150 | U25: =SUM(K25:T25) | V25: =+J25-K25-L25-M25-N25-O25-P25-T25-Q25-R25-S25 | W25: =+H25-U25 | X25: PAULINO CONEJO NAVARRETE
A26: =+A25+1 | B26: 1 | C26: 3 | D26: E | E26: =+'SITUACION COMERCIAL'!AB33 | F26: =IF('SITUACION COMERCIAL'!A33="RESERVADO",'SITUACION COMERCIAL'!S33,0) | G26: HABITAT | H26: =IF(G26="HABITAT",F26*0.025,F26*0.02) | I26: =+H26/F26 | J26: =IF('SITUACION COMERCIAL'!A33="RESERVADO",H26/2,0) | K26: 1150 | L26: 1150 | U26: =SUM(K26:T26) | V26: =+J26-K26-L26-M26-N26-O26-P26-T26-Q26-R26-S26 | W26: =+H26-U26 | X26: TRINIDAD VILLALOBOS SAAVEDRA
A27: =+A26+1 | B27: 1 | C27: 3 | D27: F | E27: =+'SITUACION COMERCIAL'!AB34 | F27: =IF('SITUACION COMERCIAL'!A34="RESERVADO",'SITUACION COMERCIAL'!S34,0) | G27: HABITAT | H27: =IF(G27="HABITAT",F27*0.025,F27*0.02) | I27: =+H27/F27 | J27: =IF('SITUACION COMERCIAL'!A34="RESERVADO",H27/2,0) | K27: 1106.25 | L27: 1193.75 | U27: =SUM(K27:T27) | V27: =+J27-K27-L27-M27-N27-O27-P27-T27-Q27-R27-S27 | W27: =+H27-U27 | X27: MARIA JOSEFA MANCHADO MORAGA
A28: =+A27+1 | B28: 1 | C28: 4 | D28: A | E28: =+'SITUACION COMERCIAL'!AB35 | F28: =IF('SITUACION COMERCIAL'!A35="RESERVADO",'SITUACION COMERCIAL'!S35,0) | G28: EDETICA | H28: =IF(G28="HABITAT",F28*0.025,F28*0.02) | I28: =+H28/F28 | J28: =IF('SITUACION COMERCIAL'!A35="RESERVADO",H28/2,0) | K28: 1383 | L28: 1383 | U28: =SUM(K28:T28) | V28: =+J28-K28-L28-M28-N28-O28-P28-T28-Q28-R28-S28 | W28: =+H28-U28 | X28: SERVILIANO VALENCIA DIAZ
A29: =+A28+1 | B29: 1 | C29: 4 | D29: B | E29: =+'SITUACION COMERCIAL'!AB36 | F29: =IF('SITUACION COMERCIAL'!A36="RESERVADO",'SITUACION COMERCIAL'!S36,0) | G29: HABITAT | H29: =IF(G29="HABITAT",F29*0.025,F29*0.02) | I29: =+H29/F29 | J29: =IF('SITUACION COMERCIAL'!A36="RESERVADO",H29/2,0) | K29: 0 | L29: 2373.75 | U29: =SUM(K29:T29) | V29: =+J29-K29-L29-M29-N29-O29-P29-T29-Q29-R29-S29 | W29: =+H29-U29 | X29: ANTONIO SANTIAGO ROMERO
A30: =+A29+1 | B30: 1 | C30: 4 | D30: C | E30: =+'SITUACION COMERCIAL'!AB37 | F30: =IF('SITUACION COMERCIAL'!A37="RESERVADO",'SITUACION COMERCIAL'!S37,0) | G30: HABITAT | H30: =IF(G30="HABITAT",F30*0.025,F30*0.02) | I30: =+H30/F30 | J30: =IF('SITUACION COMERCIAL'!A37="RESERVADO",H30/2,0) | K30: 0 | L30: 2337.5 | U30: =SUM(K30:T30) | V30: =+J30-K30-L30-M30-N30-O30-P30-T30-Q30-R30-S30 | W30: =+H30-U30 | X30: VICENTE MIGUEL SUAREZ MARTIN
A31: =+A30+1 | B31: 1 | C31: 4 | D31: D | E31: =+'SITUACION COMERCIAL'!AB38 | F31: =IF('SITUACION COMERCIAL'!A38="RESERVADO",'SITUACION COMERCIAL'!S38,0) | G31: HABITAT | H31: =IF(G31="HABITAT",F31*0.025,F31*0.02) | I31: =+H31/F31 | J31: =IF('SITUACION COMERCIAL'!A38="RESERVADO",H31/2,0) | K31: 0 | L31: 2373.75 | U31: =SUM(K31:T31) | V31: =+J31-K31-L31-M31-N31-O31-P31-T31-Q31-R31-S31 | W31: =+H31-U31 | X31: ELENA SANCHEZ RICO
A32: =+A31+1 | B32: 1 | C32: 5 | D32: A | E32: =+'SITUACION COMERCIAL'!AB39 | F32: =IF('SITUACION COMERCIAL'!A39="RESERVADO",'SITUACION COMERCIAL'!S39,0) | G32: EDETICA | H32: =IF(G32="HABITAT",F32*0.025,F32*0.02) | I32: =+H32/F32 | J32: =IF('SITUACION COMERCIAL'!A39="RESERVADO",H32/2,0) | K32: 1338.5 | L32: 1338.5 | U32: =SUM(K32:T32) | V32: 0 | W32: =+H32-U32 | X32: COMERCIAL ROMERO DE SONDEOS S.L.
A33: =+A32+1 | B33: 1 | C33: 5 | D33: B | E33: =+'SITUACION COMERCIAL'!AB40 | F33: =IF('SITUACION COMERCIAL'!A40="RESERVADO",'SITUACION COMERCIAL'!S40,0) | G33: HABITAT | H33: =IF(G33="HABITAT",F33*0.025,F33*0.02) | I33: =+H33/F33 | J33: =IF('SITUACION COMERCIAL'!A40="RESERVADO",H33/2,0) | R33: 3812.5 | U33: =SUM(K33:T33) | V33: =+J33-K33-L33-M33-N33-O33-P33-T33-Q33-R33-S33 | W33: =+H33-U33
A34: =+A33+1 | B34: 1 | C34: 5 | D34: C | E34: =+'SITUACION COMERCIAL'!AB41 | F34: =IF('SITUACION COMERCIAL'!A41="RESERVADO",'SITUACION COMERCIAL'!S41,0) | G34: HABITAT | H34: =IF(G34="HABITAT",F34*0.025,F34*0.02) | I34: =+H34/F34 | J34: =IF('SITUACION COMERCIAL'!A41="RESERVADO",H34/2,0) | K34: 1696.25 | L34: 1696.25 | U34: =SUM(K34:T34) | V34: =+J34-K34-L34-M34-N34-O34-P34-T34-Q34-R34-S34 | W34: =+H34-U34 | X34: ANGEL GUTIERREZ ROBLES
A35: =+A34+1 | B35: 2 | C35: BAJA | D35: A | E35: =+'SITUACION COMERCIAL'!AB42 | F35: =IF('SITUACION COMERCIAL'!A42="RESERVADO",'SITUACION COMERCIAL'!S42,0) | G35: HABITAT | H35: =IF(G35="HABITAT",F35*0.025,F35*0.02) | I35: =+H35/F35 | J35: =IF('SITUACION COMERCIAL'!A42="RESERVADO",H35/2,0) | S35: 4750 | U35: =SUM(K35:T35) | V35: =+J35-K35-L35-M35-N35-O35-P35-T35-Q35-R35-S35 | W35: =+H35-U35
A36: =+A35+1 | B36: 2 | C36: BAJA | D36: B | E36: =+'SITUACION COMERCIAL'!AB43 | F36: =IF('SITUACION COMERCIAL'!A43="RESERVADO",'SITUACION COMERCIAL'!S43,0) | G36: HABITAT | H36: =IF(G36="HABITAT",F36*0.025,F36*0.02) | I36: =+H36/F36 | J36: =IF('SITUACION COMERCIAL'!A43="RESERVADO",H36/2,0) | U36: =SUM(K36:T36) | V36: =+J36-K36-L36-M36-N36-O36-P36-T36-Q36-R36-S36 | W36: =+H36-U36
A37: =+A36+1 | B37: 2 | C37: BAJA | D37: C | E37: =+'SITUACION COMERCIAL'!AB44 | F37: =IF('SITUACION COMERCIAL'!A44="RESERVADO",'SITUACION COMERCIAL'!S44,0) | G37: HABITAT | H37: =IF(G37="HABITAT",F37*0.025,F37*0.02) | I37: =+H37/F37 | J37: =IF('SITUACION COMERCIAL'!A44="RESERVADO",H37/2,0) | K37: 1535.625 | L37: 1535.625 | U37: =SUM(K37:T37) | V37: =+J37-K37-L37-M37-N37-O37-P37-T37-Q37-R37-S37 | W37: =+H37-U37 | X37: CLAUDIO BORREGO DOMÍNGUEZ
A38: =+A37+1 | B38: 2 | C38: BAJA | D38: D | E38: =+'SITUACION COMERCIAL'!AB45 | F38: =IF('SITUACION COMERCIAL'!A45="RESERVADO",'SITUACION COMERCIAL'!S45,0) | G38: HABITAT | H38: =IF(G38="HABITAT",F38*0.025,F38*0.02) | I38: =+H38/F38 | J38: =IF('SITUACION COMERCIAL'!A45="RESERVADO",H38/2,0) | U38: =SUM(K38:T38) | V38: =+J38-K38-L38-M38-N38-O38-P38-T38-Q38-R38-S38 | W38: =+H38-U38
A39: =+A38+1 | B39: 2 | C39: BAJA | D39: E | E39: =+'SITUACION COMERCIAL'!AB46 | F39: =IF('SITUACION COMERCIAL'!A46="RESERVADO",'SITUACION COMERCIAL'!S46,0) | G39: HABITAT | H39: =IF(G39="HABITAT",F39*0.025,F39*0.02) | I39: =+H39/F39 | J39: =IF('SITUACION COMERCIAL'!A46="RESERVADO",H39/2,0) | K39: 1523.125 | L39: 1785.625 | U39: =SUM(K39:T39) | V39: =+J39-K39-L39-M39-N39-O39-P39-T39-Q39-R39-S39 | W39: =+H39-U39 | X39: ANTONIO MURIEL VADILLO
A40: =+A39+1 | B40: 2 | C40: 1 | D40: A | E40: =+'SITUACION COMERCIAL'!AB47 | F40: =IF('SITUACION COMERCIAL'!A47="RESERVADO",'SITUACION COMERCIAL'!S47,0) | G40: HABITAT | H40: =IF(G40="HABITAT",F40*0.025,F40*0.02) | I40: =+H40/F40 | J40: =IF('SITUACION COMERCIAL'!A47="RESERVADO",H40/2,0) | K40: 0 | L40: 4700 | U40: =SUM(K40:T40) | V40: =+J40-K40-L40-M40-N40-O40-P40-T40-Q40-R40-S40 | W40: =+H40-U40 | X40: CARMEN VICTORIA ROJAS MORENO
A41: =+A40+1 | B41: 2 | C41: 1 | D41: B | E41: =+'SITUACION COMERCIAL'!AB48 | F41: =IF('SITUACION COMERCIAL'!A48="RESERVADO",'SITUACION COMERCIAL'!S48,0) | G41: HABITAT | H41: =IF(G41="HABITAT",F41*0.025,F41*0.02) | I41: =+H41/F41 | J41: =IF('SITUACION COMERCIAL'!A48="RESERVADO",H41/2,0) | K41: 1780.625 | L41: 1780.625 | U41: =SUM(K41:T41) | V41: =+J41-K41-L41-M41-N41-O41-P41-T41-Q41-R41-S41 | W41: =+H41-U41 | X41: JOSE MANUEL ROSON JIMENEZ
A42: =+A41+1 | B42: 2 | C42: 1 | D42: C | E42: =+'SITUACION COMERCIAL'!AB49 | F42: =IF('SITUACION COMERCIAL'!A49="RESERVADO",'SITUACION COMERCIAL'!S49,0) | G42: HABITAT | H42: =IF(G42="HABITAT",F42*0.025,F42*0.02) | I42: =+H42/F42 | J42: =IF('SITUACION COMERCIAL'!A49="RESERVADO",H42/2,0) | K42: 0 | L42: 2868.75 | U42: =SUM(K42:T42) | V42: =+J42-K42-L42-M42-N42-O42-P42-T42-Q42-R42-S42 | W42: =+H42-U42 | X42: ANTONIO MANUEL PEREZ FERNANDEZ
A43: =+A42+1 | B43: 2 | C43: 1 | D43: D | E43: =+'SITUACION COMERCIAL'!AB50 | F43: =IF('SITUACION COMERCIAL'!A50="RESERVADO",'SITUACION COMERCIAL'!S50,0) | G43: HABITAT | H43: =IF(G43="HABITAT",F43*0.025,F43*0.02) | I43: =+H43/F43 | J43: =IF('SITUACION COMERCIAL'!A50="RESERVADO",H43/2,0) | K43: 993.75 | L43: 993.75 | U43: =SUM(K43:T43) | V43: =+J43-K43-L43-M43-N43-O43-P43-T43-Q43-R43-S43 | W43: =+H43-U43 | X43: FERNANDO LIMA LINEROS
A44: =+A43+1 | B44: 2 | C44: 1 | D44: E | E44: =+'SITUACION COMERCIAL'!AB51 | F44: =IF('SITUACION COMERCIAL'!A51="RESERVADO",'SITUACION COMERCIAL'!S51,0) | G44: HABITAT | H44: =IF(G44="HABITAT",F44*0.025,F44*0.02) | I44: 0.025 | J44: =IF('SITUACION COMERCIAL'!A51="RESERVADO",H44/2,0) | N44: 2886.25 | U44: =SUM(K44:T44) | V44: =+J44-K44-L44-M44-N44-O44-P44-T44-Q44-R44-S44 | W44: =+H44-U44
A45: =+A44+1 | B45: 2 | C45: 2 | D45: A | E45: =+'SITUACION COMERCIAL'!AB52 | F45: =IF('SITUACION COMERCIAL'!A52="RESERVADO",'SITUACION COMERCIAL'!S52,0) | G45: HABITAT | H45: =IF(G45="HABITAT",F45*0.025,F45*0.02) | I45: =+H45/F45 | J45: =IF('SITUACION COMERCIAL'!A52="RESERVADO",H45/2,0) | K45: 2287.5 | L45: 2287.5 | U45: =SUM(K45:T45) | V45: =+J45-K45-L45-M45-N45-O45-P45-T45-Q45-R45-S45 | W45: =+H45-U45 | X45: ALVARO MARTIN DEL POZO
A46: =+A45+1 | B46: 2 | C46: 2 | D46: B | E46: =+'SITUACION COMERCIAL'!AB53 | F46: =IF('SITUACION COMERCIAL'!A53="RESERVADO",'SITUACION COMERCIAL'!S53,0) | G46: HABITAT | H46: =IF(G46="HABITAT",F46*0.025,F46*0.02) | I46: =+H46/F46 | J46: =IF('SITUACION COMERCIAL'!A53="RESERVADO",H46/2,0) | K46: 1787.5 | L46: 1787.5 | U46: =SUM(K46:T46) | V46: =+J46-K46-L46-M46-N46-O46-P46-T46-Q46-R46-S46 | W46: =+H46-U46 | X46: ANGEL ANDERICA AREVALO
A47: =+A46+1 | B47: 2 | C47: 2 | D47: C | E47: =+'SITUACION COMERCIAL'!AB54 | F47: =IF('SITUACION COMERCIAL'!A54="RESERVADO",'SITUACION COMERCIAL'!S54,0) | G47: HABITAT | H47: =IF(G47="HABITAT",F47*0.025,F47*0.02) | I47: =+H47/F47 | J47: =IF('SITUACION COMERCIAL'!A54="RESERVADO",H47/2,0) | M47: 2906.25 | U47: =SUM(K47:T47) | V47: =+J47-K47-L47-M47-N47-O47-P47-T47-Q47-R47-S47 | W47: =+H47-U47 | X47: MARIA JOSE MERINO PIEDEHIERRO
A48: =+A47+1 | B48: 2 | C48: 2 | D48: D | E48: =+'SITUACION COMERCIAL'!AB55 | F48: =IF('SITUACION COMERCIAL'!A55="RESERVADO",'SITUACION COMERCIAL'!S55,0) | G48: HABITAT | H48: =IF(G48="HABITAT",F48*0.025,F48*0.02) | I48: =+H48/F48 | J48: =IF('SITUACION COMERCIAL'!A55="RESERVADO",H48/2,0) | K48: 979.375 | L48: 979.375 | U48: =SUM(K48:T48) | V48: =+J48-K48-L48-M48-N48-O48-P48-T48-Q48-R48-S48 | W48: =+H48-U48 | X48: MARIA DOLORES MERINO GARRIDO
A49: =+A48+1 | B49: 2 | C49: 2 | D49: E | E49: =+'SITUACION COMERCIAL'!AB56 | F49: =IF('SITUACION COMERCIAL'!A56="RESERVADO",'SITUACION COMERCIAL'!S56,0) | G49: HABITAT | H49: =IF(G49="HABITAT",F49*0.025,F49*0.02) | I49: =+H49/F49 | J49: =IF('SITUACION COMERCIAL'!A56="RESERVADO",H49/2,0) | K49: 1406.25 | L49: 1406.25 | U49: =SUM(K49:T49) | V49: =+J49-K49-L49-M49-N49-O49-P49-T49-Q49-R49-S49 | W49: =+H49-U49 | X49: JUAN JOSE GALLARDO ARCOS
A50: =+A49+1 | B50: 2 | C50: 3 | D50: A | E50: =+'SITUACION COMERCIAL'!AB57 | F50: =IF('SITUACION COMERCIAL'!A57="RESERVADO",'SITUACION COMERCIAL'!S57,0) | G50: HABITAT | H50: =IF(G50="HABITAT",F50*0.025,F50*0.02) | I50: =+H50/F50 | J50: =IF('SITUACION COMERCIAL'!A57="RESERVADO",H50/2,0) | K50: 2181.25 | L50: 2206.25 | U50: =SUM(K50:T50) | V50: =+J50-K50-L50-M50-N50-O50-P50-T50-Q50-R50-S50 | W50: =+H50-U50 | X50: MANUEL DURAN GARCIA
A51: =+A50+1 | B51: 2 | C51: 3 | D51: B | E51: =+'SITUACION COMERCIAL'!AB58 | F51: =IF('SITUACION COMERCIAL'!A58="RESERVADO",'SITUACION COMERCIAL'!S58,0) | G51: HABITAT | H51: =IF(G51="HABITAT",F51*0.025,F51*0.02) | I51: =+H51/F51 | J51: =IF('SITUACION COMERCIAL'!A58="RESERVADO",H51/2,0) | K51: 1837.5 | L51: 1837.5 | U51: =SUM(K51:T51) | V51: =+J51-K51-L51-M51-N51-O51-P51-T51-Q51-R51-S51 | W51: =+H51-U51 | X51: ANGEL CARRION AGUILERA
A52: =+A51+1 | B52: 2 | C52: 3 | D52: C | E52: =+'SITUACION COMERCIAL'!AB59 | F52: =IF('SITUACION COMERCIAL'!A59="RESERVADO",'SITUACION COMERCIAL'!S59,0) | G52: EDETICA | H52: =IF(G52="HABITAT",F52*0.025,F52*0.02) | I52: =+H52/F52 | J52: =IF('SITUACION COMERCIAL'!A59="RESERVADO",H52/2,0) | K52: 1160 | L52: 1160 | U52: =SUM(K52:T52) | V52: =+J52-K52-L52-M52-N52-O52-P52-T52-Q52-R52-S52 | W52: =+H52-U52 | X52: JOSE DIEGO HIDALGO DOMINGUEZ
A53: =+A52+1 | B53: 2 | C53: 3 | D53: D | E53: =+'SITUACION COMERCIAL'!AB60 | F53: =IF('SITUACION COMERCIAL'!A60="RESERVADO",'SITUACION COMERCIAL'!S60,0) | G53: HABITAT | H53: =IF(G53="HABITAT",F53*0.025,F53*0.02) | I53: =+H53/F53 | J53: =IF('SITUACION COMERCIAL'!A60="RESERVADO",H53/2,0) | K53: 991.875 | L53: 991.875 | U53: =SUM(K53:T53) | V53: =+J53-K53-L53-M53-N53-O53-P53-T53-Q53-R53-S53 | W53: =+H53-U53 | X53: ALBERTO GARCIA SARDIÑA
A54: =+A53+1 | B54: 2 | C54: 3 | D54: E | E54: =+'SITUACION COMERCIAL'!AB61 | F54: =IF('SITUACION COMERCIAL'!A61="RESERVADO",'SITUACION COMERCIAL'!S61,0) | G54: HABITAT | H54: =IF(G54="HABITAT",F54*0.025,F54*0.02) | I54: =+H54/F54 | J54: =IF('SITUACION COMERCIAL'!A61="RESERVADO",H54/2,0) | L54: 2925 | U54: =SUM(K54:T54) | V54: =+J54-K54-L54-M54-N54-O54-P54-T54-Q54-R54-S54 | W54: =+H54-U54 | X54: FELIPA PEREZ CORRALES
A55: =+A54+1 | B55: 3 | C55: BAJA | D55: A | E55: =+'SITUACION COMERCIAL'!AB62 | F55: =IF('SITUACION COMERCIAL'!A62="RESERVADO",'SITUACION COMERCIAL'!S62,0) | G55: HABITAT | H55: =IF(G55="HABITAT",F55*0.025,F55*0.02) | I55: =+H55/F55 | J55: =IF('SITUACION COMERCIAL'!A62="RESERVADO",H55/2,0) | K55: 1533.75 | L55: 1533.75 | U55: =SUM(K55:T55) | V55: =+J55-K55-L55-M55-N55-O55-P55-T55-Q55-R55-S55 | W55: =+H55-U55 | X55: RICARDO ANTONIO SANCHEZ HERNANDEZ
A56: =+A55+1 | B56: 3 | C56: BAJA | D56: B | E56: =+'SITUACION COMERCIAL'!AB63 | F56: =IF('SITUACION COMERCIAL'!A63="RESERVADO",'SITUACION COMERCIAL'!S63,0) | G56: HABITAT | H56: =IF(G56="HABITAT",F56*0.025,F56*0.02) | I56: =+H56/F56 | J56: =IF('SITUACION COMERCIAL'!A63="RESERVADO",H56/2,0) | U56: =SUM(K56:T56)-K56 | V56: =+J56-K56-L56-M56-N56-O56-P56-T56-Q56-R56-S56 | W56: =+H56-U56
A57: =+A56+1 | B57: 3 | C57: BAJA | D57: C | E57: =+'SITUACION COMERCIAL'!AB64 | F57: =IF('SITUACION COMERCIAL'!A64="RESERVADO",'SITUACION COMERCIAL'!S64,0) | G57: EDETICA | H57: =IF(G57="HABITAT",F57*0.025,F57*0.02) | I57: =+H57/F57 | J57: =IF('SITUACION COMERCIAL'!A64="RESERVADO",H57/2,0) | K57: 1536 | L57: 1536 | U57: =SUM(K57:T57) | V57: =+J57-K57-L57-M57-N57-O57-P57-T57-Q57-R57-S57 | W57: =+H57-U57 | X57: FELIX ARTURO MERA GALLARDO
A58: =+A57+1 | B58: 3 | C58: BAJA | D58: D | E58: =+'SITUACION COMERCIAL'!AB65 | F58: =IF('SITUACION COMERCIAL'!A65="RESERVADO",'SITUACION COMERCIAL'!S65,0) | G58: HABITAT | H58: =IF(G58="HABITAT",F58*0.025,F58*0.02) | I58: =+H58/F58 | J58: =IF('SITUACION COMERCIAL'!A65="RESERVADO",H58/2,0) | K58: 1674.375 | L58: 1674.375 | U58: =SUM(K58:T58) | V58: =+J58-K58-L58-M58-N58-O58-P58-T58-Q58-R58-S58 | W58: =+H58-U58 | X58: MANUEL LOPEZ LEON
A59: =+A58+1 | B59: 3 | C59: 1 | D59: A | E59: =+'SITUACION COMERCIAL'!AB66 | F59: =IF('SITUACION COMERCIAL'!A66="RESERVADO",'SITUACION COMERCIAL'!S66,0) | G59: HABITAT | H59: =IF(G59="HABITAT",F59*0.025,F59*0.02) | I59: =+H59/F59 | J59: =IF('SITUACION COMERCIAL'!A66="RESERVADO",H59/2,0) | K59: 1444.375 | L59: 1444.375 | U59: =SUM(K59:T59) | V59: =+J59-K59-L59-M59-N59-O59-P59-T59-Q59-R59-S59 | W59: =+H59-U59 | X59: ESPERANZA FERMOSELLE INFANTE
A60: =+A59+1 | B60: 3 | C60: 1 | D60: B | E60: =+'SITUACION COMERCIAL'!AB67 | F60: =IF('SITUACION COMERCIAL'!A67="RESERVADO",'SITUACION COMERCIAL'!S67,0) | G60: HABITAT | H60: =IF(G60="HABITAT",F60*0.025,F60*0.02) | I60: =+H60/F60 | J60: =IF('SITUACION COMERCIAL'!A67="RESERVADO",H60/2,0) | K60: 0 | L60: 3805 | U60: =SUM(K60:T60) | V60: =+J60-K60-L60-M60-N60-O60-P60-T60-Q60-R60-S60 | W60: =+H60-U60 | X60: MIGUEL SANCHEZ SANCHEZ
A61: =+A60+1 | B61: 3 | C61: 1 | D61: C | E61: =+'SITUACION COMERCIAL'!AB68 | F61: =IF('SITUACION COMERCIAL'!A68="RESERVADO",'SITUACION COMERCIAL'!S68,0) | G61: HABITAT | H61: =IF(G61="HABITAT",F61*0.025,F61*0.02) | I61: =+H61/F61 | J61: =IF('SITUACION COMERCIAL'!A68="RESERVADO",H61/2,0) | P61: 3912.5 | U61: =SUM(K61:T61) | V61: =+J61-K61-L61-M61-N61-O61-P61-T61-Q61-R61-S61 | W61: =+H61-U61
A62: =+A61+1 | B62: 3 | C62: 1 | D62: D | E62: =+'SITUACION COMERCIAL'!AB69 | F62: =IF('SITUACION COMERCIAL'!A69="RESERVADO",'SITUACION COMERCIAL'!S69,0) | G62: HABITAT | H62: =IF(G62="HABITAT",F62*0.025,F62*0.02) | I62: =+H62/F62 | J62: =IF('SITUACION COMERCIAL'!A69="RESERVADO",H62/2,0) | P62: 2993.75 | U62: =SUM(K62:T62) | V62: =+J62-K62-L62-M62-N62-O62-P62-T62-Q62-R62-S62 | W62: =+H62-U62
A63: =+A62+1 | B63: 3 | C63: 2 | D63: A | E63: =+'SITUACION COMERCIAL'!AB70 | F63: =IF('SITUACION COMERCIAL'!A70="RESERVADO",'SITUACION COMERCIAL'!S70,0) | G63: HABITAT | H63: =IF(G63="HABITAT",F63*0.025,F63*0.02) | I63: =+H63/F63 | J63: =IF('SITUACION COMERCIAL'!A70="RESERVADO",H63/2,0) | Q63: 3275 | U63: =SUM(K63:T63)-K63 | V63: =+J63-K63-L63-M63-N63-O63-P63-T63-Q63-R63-S63 | W63: =+H63-U63
A64: =+A63+1 | B64: 3 | C64: 2 | D64: B | E64: =+'SITUACION COMERCIAL'!AB71 | F64: =IF('SITUACION COMERCIAL'!A71="RESERVADO",'SITUACION COMERCIAL'!S71,0) | G64: HABITAT | H64: =IF(G64="HABITAT",F64*0.025,F64*0.02) | I64: =+H64/F64 | J64: =IF('SITUACION COMERCIAL'!A71="RESERVADO",H64/2,0) | K64: 1791.25 | L64: 1791.25 | U64: =SUM(K64:T64) | V64: =+J64-K64-L64-M64-N64-O64-P64-T64-Q64-R64-S64 | W64: =+H64-U64 | X64: JOHAN MAURICIO QUINTERO PLAZA
A65: =+A64+1 | B65: 3 | C65: 2 | D65: C | E65: =+'SITUACION COMERCIAL'!AB72 | F65: =IF('SITUACION COMERCIAL'!A72="RESERVADO",'SITUACION COMERCIAL'!S72,0) | G65: HABITAT | H65: =IF(G65="HABITAT",F65*0.025,F65*0.02) | I65: =+H65/F65 | J65: =IF('SITUACION COMERCIAL'!A72="RESERVADO",H65/2,0) | M65: 3687.5 | U65: =SUM(K65:T65) | V65: =+J65-K65-L65-M65-N65-O65-P65-T65-Q65-R65-S65 | W65: =+H65-U65 | X65: ALVARO JOSE NAVARRETE POZUECO
A66: =+A65+1 | B66: 3 | C66: 2 | D66: D | E66: =+'SITUACION COMERCIAL'!AB73 | F66: =IF('SITUACION COMERCIAL'!A73="RESERVADO",'SITUACION COMERCIAL'!S73,0) | G66: HABITAT | H66: =IF(G66="HABITAT",F66*0.025,F66*0.02) | I66: =+H66/F66 | J66: =IF('SITUACION COMERCIAL'!A73="RESERVADO",H66/2,0) | Q66: 3225 | U66: =SUM(K66:T66) | V66: =+J66-K66-L66-M66-N66-O66-P66-T66-Q66-R66-S66 | W66: =+H66-U66
A67: =+A66+1 | B67: 3 | C67: 3 | D67: A | E67: =+'SITUACION COMERCIAL'!AB74 | F67: =IF('SITUACION COMERCIAL'!A74="RESERVADO",'SITUACION COMERCIAL'!S74,0) | G67: EDETICA | H67: =IF(G67="HABITAT",F67*0.025,F67*0.02) | I67: =+H67/F67 | J67: =IF('SITUACION COMERCIAL'!A74="RESERVADO",H67/2,0) | K67: 1258.5 | L67: 1258.5 | U67: =SUM(K67:T67) | V67: =+J67-K67-L67-M67-N67-O67-P67-T67-Q67-R67-S67 | W67: =+H67-U67 | X67: ALBERTO FERNANDEZ PARRAL
A68: =+A67+1 | B68: 3 | C68: 3 | D68: B | E68: =+'SITUACION COMERCIAL'!AB75 | F68: =IF('SITUACION COMERCIAL'!A75="RESERVADO",'SITUACION COMERCIAL'!S75,0) | G68: HABITAT | H68: =IF(G68="HABITAT",F68*0.025,F68*0.02) | I68: =+H68/F68 | J68: =IF('SITUACION COMERCIAL'!A75="RESERVADO",H68/2,0) | K68: 1721.25 | L68: 2071.25 | U68: =SUM(K68:T68) | V68: =+J68-K68-L68-M68-N68-O68-P68-T68-Q68-R68-S68 | W68: =+H68-U68 | X68: MARIA GARRIDO ALVAREZ
A69: =+A68+1 | B69: 3 | C69: 3 | D69: C | E69: =+'SITUACION COMERCIAL'!AB76 | F69: =IF('SITUACION COMERCIAL'!A76="RESERVADO",'SITUACION COMERCIAL'!S76,0) | G69: HABITAT | H69: =IF(G69="HABITAT",F69*0.025,F69*0.02) | I69: =+H69/F69 | J69: =IF('SITUACION COMERCIAL'!A76="RESERVADO",H69/2,0) | K69: 1721.25 | L69: 1721.25 | U69: =SUM(K69:T69) | V69: =+J69-K69-L69-M69-N69-O69-P69-T69-Q69-R69-S69 | W69: =+H69-U69 | X69: AURELIO COLLADO BARRAGAN
A70: =+A69+1 | B70: 3 | C70: 3 | D70: D | E70: =+'SITUACION COMERCIAL'!AB77 | F70: =IF('SITUACION COMERCIAL'!A77="RESERVADO",'SITUACION COMERCIAL'!S77,0) | G70: HABITAT | H70: =IF(G70="HABITAT",F70*0.025,F70*0.02) | I70: =+H70/F70 | J70: =IF('SITUACION COMERCIAL'!A77="RESERVADO",H70/2,0) | M70: 3043.75 | U70: =SUM(K70:T70) | V70: =+J70-K70-L70-M70-N70-O70-P70-T70-Q70-R70-S70 | W70: =+H70-U70 | X70: EMILIO BENITEZ ACEDO
F71: =SUM(F5:F70) | H71: =SUM(H5:H70) | J71: =SUM(J5:J70)*2 | K71: =SUM(K5:K70) | L71: =SUM(L5:L70) | M71: =SUM(M5:M70) | N71: =SUM(N5:N70) | O71: =SUM(O5:O70) | P71: =SUM(P61:P70) | Q71: =SUM(Q5:Q70) | R71: =SUM(R5:R70) | U71: =SUM(U5:U70) | V71: =SUM(V5:V70) | W71: =SUM(W5:W70)
A72: Facturado por enuncias | N72: =+L71+M71+N71 | P72: =SUM(K71:P71) | R72: =+Q71+R71 | V72: =+Q71+R71+V71
A73: 9 | B73: 1 | C73: 1 | D73: D | E73: =+'SITUACION COMERCIAL'!AB84 | F73: =+'SITUACION COMERCIAL'!S84 | G73: HABITAT | H73: =IF(G73="HABITAT",F73*0.025,F73*0.02) | I73: =+H73/F73 | K73: 1131.25
A74: 15 | B74: 1 | C74: 2 | D74: D | E74: =+'SITUACION COMERCIAL'!AB90 | F74: =+'SITUACION COMERCIAL'!S90 | G74: HABITAT | H74: =IF(G74="HABITAT",F74*0.025,F74*0.02) | I74: =+H74/F74 | K74: 1143.75
A75: 17 | B75: 1 | C75: 2 | D75: F | E75: =+'SITUACION COMERCIAL'!AB92 | F75: =+'SITUACION COMERCIAL'!S92 | G75: HABITAT | H75: =IF(G75="HABITAT",F75*0.025,F75*0.02) | I75: =+H75/F75 | K75: 1143.75
A76: 52 | B76: 3 | C76: BAJA | D76: B | E76: =+'SITUACION COMERCIAL'!AB127 | F76: =+'SITUACION COMERCIAL'!S127 | G76: HABITAT | H76: =IF(G76="HABITAT",F76*0.025,F76*0.02) | I76: =+H76/F76 | K76: 1744.375
A77: 59 | B77: 3 | C77: 2 | D77: A | E77: =+'SITUACION COMERCIAL'!AB134 | F77: =+'SITUACION COMERCIAL'!S134 | G77: HABITAT | H77: =IF(G77="HABITAT",F77*0.025,F77*0.02) | I77: =+H77/F77 | K77: 1455.625
H78: =SUM(H73:H77) | K78: =SUM(K73:K77) | N78: =+L71 | O78: 45413
K79: =+K71+K78 | N79: =+M71 | O79: 45474
F80: =+F71-'SITUACION COMERCIAL'!#REF! | G80: =+F80*0.025 | N80: =+N71 | O80: 45505
H81: =+H71-G80 | N81: =+O71
N82: =+P71
